<?xml version='1.0' encoding='UTF-8' ?>
<ARM10A>
	<ALIAS id="ddm_tables">
		<ID id="ddm_tables">DDM_TABLES</ID>
		<RECORD id="ddm_tables.arm10a">
			<DD_TABLE_ALIAS id="ddm_tables.arm10a">ARM10A          </DD_TABLE_ALIAS>
			<DD_ALIAS_DESC id="ddm_tables.arm10a">V6 Terms Code</DD_ALIAS_DESC>
			<DD_FILE_NAME id="ddm_tables.arm10a">ARM-10</DD_FILE_NAME>
			<DD_TABLE_PATH id="ddm_tables.arm10a">[+V6DATA]</DD_TABLE_PATH>
			<DD_ALIAS_TYPE id="ddm_tables.arm10a">K</DD_ALIAS_TYPE>
			<DD_KEY_LENGTH id="ddm_tables.arm10a">0</DD_KEY_LENGTH>
			<DD_NBR_RECORD id="ddm_tables.arm10a">0</DD_NBR_RECORD>
			<DD_RECORD_LEN id="ddm_tables.arm10a">0</DD_RECORD_LEN>
			<DD_SYSTEM_REC id="ddm_tables.arm10a"></DD_SYSTEM_REC>
			<RESTRICT_CREATE id="ddm_tables.arm10a">Y</RESTRICT_CREATE>
			<RESTRICT_REBUILD id="ddm_tables.arm10a">N</RESTRICT_REBUILD>
			<RESTRICT_AUTOADD id="ddm_tables.arm10a">Y</RESTRICT_AUTOADD>
			<ASC_COMP_ID id="ddm_tables.arm10a">00000000</ASC_COMP_ID>
			<ASC_PROD_ID id="ddm_tables.arm10a">V6H</ASC_PROD_ID>
			<ASC_VERSION_ID id="ddm_tables.arm10a">18.0      </ASC_VERSION_ID>
			<ASC_LICENSE_ID id="ddm_tables.arm10a"></ASC_LICENSE_ID>
			<DD_EXPORT_DATA id="ddm_tables.arm10a">Y</DD_EXPORT_DATA>
			<DD_CREATE_DATE id="ddm_tables.arm10a">2457673</DD_CREATE_DATE>
			<DD_LSTREV_DATE id="ddm_tables.arm10a">20191126</DD_LSTREV_DATE>
			<DD_LSTSYNC_DATE id="ddm_tables.arm10a">20191126</DD_LSTSYNC_DATE>
			<DD_LSTSYNC_TIME id="ddm_tables.arm10a">130225</DD_LSTSYNC_TIME>
			<DD_ATTR_ATAB id="ddm_tables.arm10a"></DD_ATTR_ATAB>
			<DD_ATTR_CPGM id="ddm_tables.arm10a"></DD_ATTR_CPGM>
			<DD_ATTR_DKNM id="ddm_tables.arm10a"></DD_ATTR_DKNM>
			<DD_ATTR_FIMG id="ddm_tables.arm10a"></DD_ATTR_FIMG>
			<DD_ATTR_FTYP id="ddm_tables.arm10a">T</DD_ATTR_FTYP>
			<DD_ATTR_HELP id="ddm_tables.arm10a"></DD_ATTR_HELP>
			<DD_ATTR_IKEY id="ddm_tables.arm10a"></DD_ATTR_IKEY>
			<DD_ATTR_IDEF id="ddm_tables.arm10a"></DD_ATTR_IDEF>
			<DD_ATTR_MRES id="ddm_tables.arm10a"></DD_ATTR_MRES>
			<DD_ATTR_NOTE id="ddm_tables.arm10a"></DD_ATTR_NOTE>
			<DD_ATTR_PCAL id="ddm_tables.arm10a"></DD_ATTR_PCAL>
			<DD_ATTR_PRUN id="ddm_tables.arm10a"></DD_ATTR_PRUN>
			<DD_ATTR_PTAB id="ddm_tables.arm10a"></DD_ATTR_PTAB>
			<DD_ATTR_SLEV id="ddm_tables.arm10a"></DD_ATTR_SLEV>
			<DD_ATTR_WINT id="ddm_tables.arm10a">V6 Terms Code</DD_ATTR_WINT>
			<SQL_DB_ALIAS id="ddm_tables.arm10a"></SQL_DB_ALIAS>
			<SQL_CATALOG id="ddm_tables.arm10a"></SQL_CATALOG>
			<SQL_SCHEMA id="ddm_tables.arm10a"></SQL_SCHEMA>
			<SQL_TABLE id="ddm_tables.arm10a"></SQL_TABLE>
			<DD_ATTR_FONT id="ddm_tables.arm10a"></DD_ATTR_FONT>
			<DD_ATTR_STYL id="ddm_tables.arm10a"></DD_ATTR_STYL>
			<DD_ADMIN_BACKUP id="ddm_tables.arm10a"></DD_ADMIN_BACKUP>
			<DD_ATTR_RSET id="ddm_tables.arm10a"></DD_ATTR_RSET>
			<DD_ATTR_IGNR id="ddm_tables.arm10a"></DD_ATTR_IGNR>
			<DD_ATTR_RPOS id="ddm_tables.arm10a"></DD_ATTR_RPOS>
			<DD_ATTR_XPOS id="ddm_tables.arm10a"></DD_ATTR_XPOS>
			<DD_ATTR_YPOS id="ddm_tables.arm10a"></DD_ATTR_YPOS>
			<DD_ATTR_FWID id="ddm_tables.arm10a"></DD_ATTR_FWID>
			<DD_ATTR_FHGT id="ddm_tables.arm10a"></DD_ATTR_FHGT>
			<DD_ATTR_PADW id="ddm_tables.arm10a"></DD_ATTR_PADW>
			<DD_ATTR_PADH id="ddm_tables.arm10a"></DD_ATTR_PADH>
			<DD_ATTR_PADG id="ddm_tables.arm10a"></DD_ATTR_PADG>
		</RECORD>
	</ALIAS>
	<ALIAS id="ddm_table_opts">
		<ID id="ddm_table_opts">DDM_TABLE_OPTS</ID>
		<RECORD id="ddm_table_opts.arm10aa">
			<DD_TABLE_ALIAS id="ddm_table_opts.arm10aa">ARM10A          </DD_TABLE_ALIAS>
			<DD_ATTR_OPTS id="ddm_table_opts.arm10aa">A</DD_ATTR_OPTS>
		</RECORD>
		<RECORD id="ddm_table_opts.arm10an">
			<DD_TABLE_ALIAS id="ddm_table_opts.arm10an">ARM10A          </DD_TABLE_ALIAS>
			<DD_ATTR_OPTS id="ddm_table_opts.arm10an">N</DD_ATTR_OPTS>
		</RECORD>
		<RECORD id="ddm_table_opts.arm10ap">
			<DD_TABLE_ALIAS id="ddm_table_opts.arm10ap">ARM10A          </DD_TABLE_ALIAS>
			<DD_ATTR_OPTS id="ddm_table_opts.arm10ap">P</DD_ATTR_OPTS>
		</RECORD>
		<RECORD id="ddm_table_opts.arm10au">
			<DD_TABLE_ALIAS id="ddm_table_opts.arm10au">ARM10A          </DD_TABLE_ALIAS>
			<DD_ATTR_OPTS id="ddm_table_opts.arm10au">U</DD_ATTR_OPTS>
		</RECORD>
		<RECORD id="ddm_table_opts.arm10av">
			<DD_TABLE_ALIAS id="ddm_table_opts.arm10av">ARM10A          </DD_TABLE_ALIAS>
			<DD_ATTR_OPTS id="ddm_table_opts.arm10av">V</DD_ATTR_OPTS>
		</RECORD>
	</ALIAS>
	<ALIAS id="ddm_table_tpls">
		<ID id="ddm_table_tpls">DDM_TABLE_TPLS</ID>
		<RECORD id="ddm_table_tpls.arm10a">
			<DD_TABLE_ALIAS id="ddm_table_tpls.arm10a">ARM10A          </DD_TABLE_ALIAS>
			<DD_FILE_NAME id="ddm_table_tpls.arm10a">ARM-10</DD_FILE_NAME>
			<DD_TABLE_TPL id="ddm_table_tpls.arm10a">v6_firm_id:c(2),v6_record_id_a:c(1),v6_terms_code:c(2),v6_code_desc:c(20),v6_prox_or_days:c(1),v6_cred_hold:c(1),v6_rsrvd_str:c(3*),v6_disc_percent:n(7*),v6_inv_days_due:n(7*),v6_disc_days:n(7*)</DD_TABLE_TPL>
		</RECORD>
	</ALIAS>
	<ALIAS id="ddm_keys">
		<ID id="ddm_keys">DDM_KEYS</ID>
		<RECORD id="ddm_keys.arm10a00">
			<DD_TABLE_ALIAS id="ddm_keys.arm10a00">ARM10A          </DD_TABLE_ALIAS>
			<DD_KEY_NUMBER id="ddm_keys.arm10a00">00</DD_KEY_NUMBER>
			<DD_KEY_DESC id="ddm_keys.arm10a00">Primary</DD_KEY_DESC>
			<DD_KEY_ID id="ddm_keys.arm10a00">PRIMARY         </DD_KEY_ID>
			<DD_KEY_AUTO_GEN id="ddm_keys.arm10a00"></DD_KEY_AUTO_GEN>
		</RECORD>
	</ALIAS>
	<ALIAS id="ddm_key_segs">
		<ID id="ddm_key_segs">DDM_KEY_SEGS</ID>
		<RECORD id="ddm_key_segs.arm10a0001">
			<DD_TABLE_ALIAS id="ddm_key_segs.arm10a0001">ARM10A          </DD_TABLE_ALIAS>
			<DD_KEY_NUMBER id="ddm_key_segs.arm10a0001">00</DD_KEY_NUMBER>
			<DD_SEGMENT_SEQ id="ddm_key_segs.arm10a0001">01</DD_SEGMENT_SEQ>
			<DD_SEGMENT_COL id="ddm_key_segs.arm10a0001">V6_FIRM_ID</DD_SEGMENT_COL>
			<DD_SEGMENT_POS id="ddm_key_segs.arm10a0001">0</DD_SEGMENT_POS>
			<DD_SEGMENT_OFF id="ddm_key_segs.arm10a0001">0</DD_SEGMENT_OFF>
			<DD_SEGMENT_LEN id="ddm_key_segs.arm10a0001">0</DD_SEGMENT_LEN>
			<DD_SEGMENT_SORT id="ddm_key_segs.arm10a0001">N</DD_SEGMENT_SORT>
			<DD_SEGMENT_UNIQ id="ddm_key_segs.arm10a0001">N</DD_SEGMENT_UNIQ>
			<DD_SEGMENT_MATH id="ddm_key_segs.arm10a0001">N</DD_SEGMENT_MATH>
			<DD_SEGMENT_NUM id="ddm_key_segs.arm10a0001"></DD_SEGMENT_NUM>
		</RECORD>
		<RECORD id="ddm_key_segs.arm10a0002">
			<DD_TABLE_ALIAS id="ddm_key_segs.arm10a0002">ARM10A          </DD_TABLE_ALIAS>
			<DD_KEY_NUMBER id="ddm_key_segs.arm10a0002">00</DD_KEY_NUMBER>
			<DD_SEGMENT_SEQ id="ddm_key_segs.arm10a0002">02</DD_SEGMENT_SEQ>
			<DD_SEGMENT_COL id="ddm_key_segs.arm10a0002">V6_RECORD_ID_A</DD_SEGMENT_COL>
			<DD_SEGMENT_POS id="ddm_key_segs.arm10a0002">0</DD_SEGMENT_POS>
			<DD_SEGMENT_OFF id="ddm_key_segs.arm10a0002">0</DD_SEGMENT_OFF>
			<DD_SEGMENT_LEN id="ddm_key_segs.arm10a0002">0</DD_SEGMENT_LEN>
			<DD_SEGMENT_SORT id="ddm_key_segs.arm10a0002">N</DD_SEGMENT_SORT>
			<DD_SEGMENT_UNIQ id="ddm_key_segs.arm10a0002">N</DD_SEGMENT_UNIQ>
			<DD_SEGMENT_MATH id="ddm_key_segs.arm10a0002">N</DD_SEGMENT_MATH>
			<DD_SEGMENT_NUM id="ddm_key_segs.arm10a0002"></DD_SEGMENT_NUM>
		</RECORD>
		<RECORD id="ddm_key_segs.arm10a0003">
			<DD_TABLE_ALIAS id="ddm_key_segs.arm10a0003">ARM10A          </DD_TABLE_ALIAS>
			<DD_KEY_NUMBER id="ddm_key_segs.arm10a0003">00</DD_KEY_NUMBER>
			<DD_SEGMENT_SEQ id="ddm_key_segs.arm10a0003">03</DD_SEGMENT_SEQ>
			<DD_SEGMENT_COL id="ddm_key_segs.arm10a0003">V6_TERMS_CODE</DD_SEGMENT_COL>
			<DD_SEGMENT_POS id="ddm_key_segs.arm10a0003">0</DD_SEGMENT_POS>
			<DD_SEGMENT_OFF id="ddm_key_segs.arm10a0003">0</DD_SEGMENT_OFF>
			<DD_SEGMENT_LEN id="ddm_key_segs.arm10a0003">0</DD_SEGMENT_LEN>
			<DD_SEGMENT_SORT id="ddm_key_segs.arm10a0003">N</DD_SEGMENT_SORT>
			<DD_SEGMENT_UNIQ id="ddm_key_segs.arm10a0003">N</DD_SEGMENT_UNIQ>
			<DD_SEGMENT_MATH id="ddm_key_segs.arm10a0003">N</DD_SEGMENT_MATH>
			<DD_SEGMENT_NUM id="ddm_key_segs.arm10a0003"></DD_SEGMENT_NUM>
		</RECORD>
	</ALIAS>
	<ALIAS id="ddm_table_cols">
		<ID id="ddm_table_cols">DDM_TABLE_COLS</ID>
		<RECORD id="ddm_table_cols.arm10a001">
			<DD_TABLE_ALIAS id="ddm_table_cols.arm10a001">ARM10A          </DD_TABLE_ALIAS>
			<DD_SEQUENCE id="ddm_table_cols.arm10a001">001</DD_SEQUENCE>
			<DD_DATA_NAME id="ddm_table_cols.arm10a001">V6_FIRM_ID      </DD_DATA_NAME>
			<DD_DVAR_NAME id="ddm_table_cols.arm10a001">V6_FIRM_ID      </DD_DVAR_NAME>
			<DD_COL_REPEATS id="ddm_table_cols.arm10a001">0</DD_COL_REPEATS>
			<DD_COL_OCCURS id="ddm_table_cols.arm10a001">0</DD_COL_OCCURS>
			<DD_FIELD_DELIM id="ddm_table_cols.arm10a001">N</DD_FIELD_DELIM>
			<DD_DELIM_CHAR id="ddm_table_cols.arm10a001">0A</DD_DELIM_CHAR>
			<DD_SYSTEM_REC id="ddm_table_cols.arm10a001"></DD_SYSTEM_REC>
			<DD_SYSTEM_ID id="ddm_table_cols.arm10a001"></DD_SYSTEM_ID>
			<DD_MASK_TYPE id="ddm_table_cols.arm10a001"></DD_MASK_TYPE>
			<DD_CREATE_DATE id="ddm_table_cols.arm10a001">20161011</DD_CREATE_DATE>
			<DD_LSTREV_DATE id="ddm_table_cols.arm10a001">20161011</DD_LSTREV_DATE>
			<DD_ATTR_ABLC id="ddm_table_cols.arm10a001"></DD_ATTR_ABLC>
			<DD_ATTR_ABLV id="ddm_table_cols.arm10a001"></DD_ATTR_ABLV>
			<DD_ATTR_CPGM id="ddm_table_cols.arm10a001"></DD_ATTR_CPGM>
			<DD_ATTR_COLW id="ddm_table_cols.arm10a001">0</DD_ATTR_COLW>
			<DD_ATTR_CTLX id="ddm_table_cols.arm10a001"></DD_ATTR_CTLX>
			<DD_ATTR_CTLY id="ddm_table_cols.arm10a001"></DD_ATTR_CTLY>
			<DD_ATTR_CTLW id="ddm_table_cols.arm10a001"></DD_ATTR_CTLW>
			<DD_ATTR_CTLH id="ddm_table_cols.arm10a001"></DD_ATTR_CTLH>
			<DD_ATTR_DFLT id="ddm_table_cols.arm10a001"></DD_ATTR_DFLT>
			<DD_ATTR_DRLE id="ddm_table_cols.arm10a001"></DD_ATTR_DRLE>
			<DD_ATTR_GHDR id="ddm_table_cols.arm10a001"></DD_ATTR_GHDR>
			<DD_ATTR_IDEF id="ddm_table_cols.arm10a001"></DD_ATTR_IDEF>
			<DD_ATTR_LABL id="ddm_table_cols.arm10a001"></DD_ATTR_LABL>
			<DD_ATTR_LABS id="ddm_table_cols.arm10a001"></DD_ATTR_LABS>
			<DD_ATTR_MLAN id="ddm_table_cols.arm10a001">N</DD_ATTR_MLAN>
			<DD_ATTR_MINL id="ddm_table_cols.arm10a001"></DD_ATTR_MINL>
			<DD_ATTR_MAXL id="ddm_table_cols.arm10a001"></DD_ATTR_MAXL>
			<DD_ATTR_MINV id="ddm_table_cols.arm10a001"></DD_ATTR_MINV>
			<DD_ATTR_MAXV id="ddm_table_cols.arm10a001"></DD_ATTR_MAXV>
			<DD_ATTR_PROM id="ddm_table_cols.arm10a001"></DD_ATTR_PROM>
			<DD_ATTR_PVAL id="ddm_table_cols.arm10a001"></DD_ATTR_PVAL>
			<DD_ATTR_SLEV id="ddm_table_cols.arm10a001"></DD_ATTR_SLEV>
			<DD_ATTR_TABG id="ddm_table_cols.arm10a001"></DD_ATTR_TABG>
			<DD_ATTR_TIND id="ddm_table_cols.arm10a001">1</DD_ATTR_TIND>
			<DD_ATTR_HELP id="ddm_table_cols.arm10a001"></DD_ATTR_HELP>
			<SQL_COLUMN_NAME id="ddm_table_cols.arm10a001">V6_FIRM_ID</SQL_COLUMN_NAME>
			<DD_ATTR_FONT id="ddm_table_cols.arm10a001"></DD_ATTR_FONT>
			<DD_ATTR_STYL id="ddm_table_cols.arm10a001"></DD_ATTR_STYL>
			<DD_ATTR_FTSR id="ddm_table_cols.arm10a001">N</DD_ATTR_FTSR>
			<DD_ATTR_CWID id="ddm_table_cols.arm10a001"></DD_ATTR_CWID>
			<DD_ATTR_CTLI id="ddm_table_cols.arm10a001"></DD_ATTR_CTLI>
			<DD_ATTR_CTLN id="ddm_table_cols.arm10a001"></DD_ATTR_CTLN>
			<DD_ATTR_CTLC id="ddm_table_cols.arm10a001"></DD_ATTR_CTLC>
			<DD_ATTR_RADG id="ddm_table_cols.arm10a001"></DD_ATTR_RADG>
			<DD_ATTR_RKEY id="ddm_table_cols.arm10a001">Y</DD_ATTR_RKEY>
			<DD_ATTR_BTNS id="ddm_table_cols.arm10a001"></DD_ATTR_BTNS>
		</RECORD>
		<RECORD id="ddm_table_cols.arm10a002">
			<DD_TABLE_ALIAS id="ddm_table_cols.arm10a002">ARM10A          </DD_TABLE_ALIAS>
			<DD_SEQUENCE id="ddm_table_cols.arm10a002">002</DD_SEQUENCE>
			<DD_DATA_NAME id="ddm_table_cols.arm10a002">V6_RECORD_ID_A  </DD_DATA_NAME>
			<DD_DVAR_NAME id="ddm_table_cols.arm10a002">V6_RECORD_ID_A  </DD_DVAR_NAME>
			<DD_COL_REPEATS id="ddm_table_cols.arm10a002">0</DD_COL_REPEATS>
			<DD_COL_OCCURS id="ddm_table_cols.arm10a002">0</DD_COL_OCCURS>
			<DD_FIELD_DELIM id="ddm_table_cols.arm10a002">N</DD_FIELD_DELIM>
			<DD_DELIM_CHAR id="ddm_table_cols.arm10a002">0A</DD_DELIM_CHAR>
			<DD_SYSTEM_REC id="ddm_table_cols.arm10a002"></DD_SYSTEM_REC>
			<DD_SYSTEM_ID id="ddm_table_cols.arm10a002"></DD_SYSTEM_ID>
			<DD_MASK_TYPE id="ddm_table_cols.arm10a002"></DD_MASK_TYPE>
			<DD_CREATE_DATE id="ddm_table_cols.arm10a002">20161011</DD_CREATE_DATE>
			<DD_LSTREV_DATE id="ddm_table_cols.arm10a002">20161011</DD_LSTREV_DATE>
			<DD_ATTR_ABLC id="ddm_table_cols.arm10a002"></DD_ATTR_ABLC>
			<DD_ATTR_ABLV id="ddm_table_cols.arm10a002"></DD_ATTR_ABLV>
			<DD_ATTR_CPGM id="ddm_table_cols.arm10a002"></DD_ATTR_CPGM>
			<DD_ATTR_COLW id="ddm_table_cols.arm10a002">0</DD_ATTR_COLW>
			<DD_ATTR_CTLX id="ddm_table_cols.arm10a002"></DD_ATTR_CTLX>
			<DD_ATTR_CTLY id="ddm_table_cols.arm10a002"></DD_ATTR_CTLY>
			<DD_ATTR_CTLW id="ddm_table_cols.arm10a002"></DD_ATTR_CTLW>
			<DD_ATTR_CTLH id="ddm_table_cols.arm10a002"></DD_ATTR_CTLH>
			<DD_ATTR_DFLT id="ddm_table_cols.arm10a002"></DD_ATTR_DFLT>
			<DD_ATTR_DRLE id="ddm_table_cols.arm10a002"></DD_ATTR_DRLE>
			<DD_ATTR_GHDR id="ddm_table_cols.arm10a002"></DD_ATTR_GHDR>
			<DD_ATTR_IDEF id="ddm_table_cols.arm10a002"></DD_ATTR_IDEF>
			<DD_ATTR_LABL id="ddm_table_cols.arm10a002"></DD_ATTR_LABL>
			<DD_ATTR_LABS id="ddm_table_cols.arm10a002"></DD_ATTR_LABS>
			<DD_ATTR_MLAN id="ddm_table_cols.arm10a002">N</DD_ATTR_MLAN>
			<DD_ATTR_MINL id="ddm_table_cols.arm10a002"></DD_ATTR_MINL>
			<DD_ATTR_MAXL id="ddm_table_cols.arm10a002"></DD_ATTR_MAXL>
			<DD_ATTR_MINV id="ddm_table_cols.arm10a002"></DD_ATTR_MINV>
			<DD_ATTR_MAXV id="ddm_table_cols.arm10a002"></DD_ATTR_MAXV>
			<DD_ATTR_PROM id="ddm_table_cols.arm10a002"></DD_ATTR_PROM>
			<DD_ATTR_PVAL id="ddm_table_cols.arm10a002"></DD_ATTR_PVAL>
			<DD_ATTR_SLEV id="ddm_table_cols.arm10a002"></DD_ATTR_SLEV>
			<DD_ATTR_TABG id="ddm_table_cols.arm10a002"></DD_ATTR_TABG>
			<DD_ATTR_TIND id="ddm_table_cols.arm10a002">2</DD_ATTR_TIND>
			<DD_ATTR_HELP id="ddm_table_cols.arm10a002"></DD_ATTR_HELP>
			<SQL_COLUMN_NAME id="ddm_table_cols.arm10a002">V6_RECORD_ID_A</SQL_COLUMN_NAME>
			<DD_ATTR_FONT id="ddm_table_cols.arm10a002"></DD_ATTR_FONT>
			<DD_ATTR_STYL id="ddm_table_cols.arm10a002"></DD_ATTR_STYL>
			<DD_ATTR_FTSR id="ddm_table_cols.arm10a002">N</DD_ATTR_FTSR>
			<DD_ATTR_CWID id="ddm_table_cols.arm10a002"></DD_ATTR_CWID>
			<DD_ATTR_CTLI id="ddm_table_cols.arm10a002">3001</DD_ATTR_CTLI>
			<DD_ATTR_CTLN id="ddm_table_cols.arm10a002">ine_v6_record_id_a</DD_ATTR_CTLN>
			<DD_ATTR_CTLC id="ddm_table_cols.arm10a002">0</DD_ATTR_CTLC>
			<DD_ATTR_RADG id="ddm_table_cols.arm10a002"></DD_ATTR_RADG>
			<DD_ATTR_RKEY id="ddm_table_cols.arm10a002">Y</DD_ATTR_RKEY>
			<DD_ATTR_BTNS id="ddm_table_cols.arm10a002"></DD_ATTR_BTNS>
		</RECORD>
		<RECORD id="ddm_table_cols.arm10a003">
			<DD_TABLE_ALIAS id="ddm_table_cols.arm10a003">ARM10A          </DD_TABLE_ALIAS>
			<DD_SEQUENCE id="ddm_table_cols.arm10a003">003</DD_SEQUENCE>
			<DD_DATA_NAME id="ddm_table_cols.arm10a003">V6_TERMS_CODE   </DD_DATA_NAME>
			<DD_DVAR_NAME id="ddm_table_cols.arm10a003">V6_TERMS_CODE   </DD_DVAR_NAME>
			<DD_COL_REPEATS id="ddm_table_cols.arm10a003">0</DD_COL_REPEATS>
			<DD_COL_OCCURS id="ddm_table_cols.arm10a003">0</DD_COL_OCCURS>
			<DD_FIELD_DELIM id="ddm_table_cols.arm10a003">N</DD_FIELD_DELIM>
			<DD_DELIM_CHAR id="ddm_table_cols.arm10a003">0A</DD_DELIM_CHAR>
			<DD_SYSTEM_REC id="ddm_table_cols.arm10a003"></DD_SYSTEM_REC>
			<DD_SYSTEM_ID id="ddm_table_cols.arm10a003"></DD_SYSTEM_ID>
			<DD_MASK_TYPE id="ddm_table_cols.arm10a003"></DD_MASK_TYPE>
			<DD_CREATE_DATE id="ddm_table_cols.arm10a003">20161011</DD_CREATE_DATE>
			<DD_LSTREV_DATE id="ddm_table_cols.arm10a003">20161011</DD_LSTREV_DATE>
			<DD_ATTR_ABLC id="ddm_table_cols.arm10a003"></DD_ATTR_ABLC>
			<DD_ATTR_ABLV id="ddm_table_cols.arm10a003"></DD_ATTR_ABLV>
			<DD_ATTR_CPGM id="ddm_table_cols.arm10a003"></DD_ATTR_CPGM>
			<DD_ATTR_COLW id="ddm_table_cols.arm10a003">0</DD_ATTR_COLW>
			<DD_ATTR_CTLX id="ddm_table_cols.arm10a003"></DD_ATTR_CTLX>
			<DD_ATTR_CTLY id="ddm_table_cols.arm10a003"></DD_ATTR_CTLY>
			<DD_ATTR_CTLW id="ddm_table_cols.arm10a003"></DD_ATTR_CTLW>
			<DD_ATTR_CTLH id="ddm_table_cols.arm10a003"></DD_ATTR_CTLH>
			<DD_ATTR_DFLT id="ddm_table_cols.arm10a003"></DD_ATTR_DFLT>
			<DD_ATTR_DRLE id="ddm_table_cols.arm10a003"></DD_ATTR_DRLE>
			<DD_ATTR_GHDR id="ddm_table_cols.arm10a003"></DD_ATTR_GHDR>
			<DD_ATTR_IDEF id="ddm_table_cols.arm10a003"></DD_ATTR_IDEF>
			<DD_ATTR_LABL id="ddm_table_cols.arm10a003"></DD_ATTR_LABL>
			<DD_ATTR_LABS id="ddm_table_cols.arm10a003"></DD_ATTR_LABS>
			<DD_ATTR_MLAN id="ddm_table_cols.arm10a003">N</DD_ATTR_MLAN>
			<DD_ATTR_MINL id="ddm_table_cols.arm10a003"></DD_ATTR_MINL>
			<DD_ATTR_MAXL id="ddm_table_cols.arm10a003"></DD_ATTR_MAXL>
			<DD_ATTR_MINV id="ddm_table_cols.arm10a003"></DD_ATTR_MINV>
			<DD_ATTR_MAXV id="ddm_table_cols.arm10a003"></DD_ATTR_MAXV>
			<DD_ATTR_PROM id="ddm_table_cols.arm10a003"></DD_ATTR_PROM>
			<DD_ATTR_PVAL id="ddm_table_cols.arm10a003"></DD_ATTR_PVAL>
			<DD_ATTR_SLEV id="ddm_table_cols.arm10a003"></DD_ATTR_SLEV>
			<DD_ATTR_TABG id="ddm_table_cols.arm10a003"></DD_ATTR_TABG>
			<DD_ATTR_TIND id="ddm_table_cols.arm10a003">3</DD_ATTR_TIND>
			<DD_ATTR_HELP id="ddm_table_cols.arm10a003"></DD_ATTR_HELP>
			<SQL_COLUMN_NAME id="ddm_table_cols.arm10a003">V6_TERMS_CODE</SQL_COLUMN_NAME>
			<DD_ATTR_FONT id="ddm_table_cols.arm10a003"></DD_ATTR_FONT>
			<DD_ATTR_STYL id="ddm_table_cols.arm10a003"></DD_ATTR_STYL>
			<DD_ATTR_FTSR id="ddm_table_cols.arm10a003">N</DD_ATTR_FTSR>
			<DD_ATTR_CWID id="ddm_table_cols.arm10a003"></DD_ATTR_CWID>
			<DD_ATTR_CTLI id="ddm_table_cols.arm10a003">3002</DD_ATTR_CTLI>
			<DD_ATTR_CTLN id="ddm_table_cols.arm10a003">ine_v6_terms_code</DD_ATTR_CTLN>
			<DD_ATTR_CTLC id="ddm_table_cols.arm10a003">0</DD_ATTR_CTLC>
			<DD_ATTR_RADG id="ddm_table_cols.arm10a003"></DD_ATTR_RADG>
			<DD_ATTR_RKEY id="ddm_table_cols.arm10a003">Y</DD_ATTR_RKEY>
			<DD_ATTR_BTNS id="ddm_table_cols.arm10a003"></DD_ATTR_BTNS>
		</RECORD>
		<RECORD id="ddm_table_cols.arm10a004">
			<DD_TABLE_ALIAS id="ddm_table_cols.arm10a004">ARM10A          </DD_TABLE_ALIAS>
			<DD_SEQUENCE id="ddm_table_cols.arm10a004">004</DD_SEQUENCE>
			<DD_DATA_NAME id="ddm_table_cols.arm10a004">V6_CODE_DESC    </DD_DATA_NAME>
			<DD_DVAR_NAME id="ddm_table_cols.arm10a004">V6_CODE_DESC    </DD_DVAR_NAME>
			<DD_COL_REPEATS id="ddm_table_cols.arm10a004">0</DD_COL_REPEATS>
			<DD_COL_OCCURS id="ddm_table_cols.arm10a004">0</DD_COL_OCCURS>
			<DD_FIELD_DELIM id="ddm_table_cols.arm10a004">N</DD_FIELD_DELIM>
			<DD_DELIM_CHAR id="ddm_table_cols.arm10a004">0A</DD_DELIM_CHAR>
			<DD_SYSTEM_REC id="ddm_table_cols.arm10a004"></DD_SYSTEM_REC>
			<DD_SYSTEM_ID id="ddm_table_cols.arm10a004"></DD_SYSTEM_ID>
			<DD_MASK_TYPE id="ddm_table_cols.arm10a004"></DD_MASK_TYPE>
			<DD_CREATE_DATE id="ddm_table_cols.arm10a004">20161011</DD_CREATE_DATE>
			<DD_LSTREV_DATE id="ddm_table_cols.arm10a004">20161011</DD_LSTREV_DATE>
			<DD_ATTR_ABLC id="ddm_table_cols.arm10a004"></DD_ATTR_ABLC>
			<DD_ATTR_ABLV id="ddm_table_cols.arm10a004"></DD_ATTR_ABLV>
			<DD_ATTR_CPGM id="ddm_table_cols.arm10a004"></DD_ATTR_CPGM>
			<DD_ATTR_COLW id="ddm_table_cols.arm10a004">0</DD_ATTR_COLW>
			<DD_ATTR_CTLX id="ddm_table_cols.arm10a004"></DD_ATTR_CTLX>
			<DD_ATTR_CTLY id="ddm_table_cols.arm10a004"></DD_ATTR_CTLY>
			<DD_ATTR_CTLW id="ddm_table_cols.arm10a004"></DD_ATTR_CTLW>
			<DD_ATTR_CTLH id="ddm_table_cols.arm10a004"></DD_ATTR_CTLH>
			<DD_ATTR_DFLT id="ddm_table_cols.arm10a004"></DD_ATTR_DFLT>
			<DD_ATTR_DRLE id="ddm_table_cols.arm10a004"></DD_ATTR_DRLE>
			<DD_ATTR_GHDR id="ddm_table_cols.arm10a004"></DD_ATTR_GHDR>
			<DD_ATTR_IDEF id="ddm_table_cols.arm10a004"></DD_ATTR_IDEF>
			<DD_ATTR_LABL id="ddm_table_cols.arm10a004"></DD_ATTR_LABL>
			<DD_ATTR_LABS id="ddm_table_cols.arm10a004"></DD_ATTR_LABS>
			<DD_ATTR_MLAN id="ddm_table_cols.arm10a004">N</DD_ATTR_MLAN>
			<DD_ATTR_MINL id="ddm_table_cols.arm10a004"></DD_ATTR_MINL>
			<DD_ATTR_MAXL id="ddm_table_cols.arm10a004"></DD_ATTR_MAXL>
			<DD_ATTR_MINV id="ddm_table_cols.arm10a004"></DD_ATTR_MINV>
			<DD_ATTR_MAXV id="ddm_table_cols.arm10a004"></DD_ATTR_MAXV>
			<DD_ATTR_PROM id="ddm_table_cols.arm10a004"></DD_ATTR_PROM>
			<DD_ATTR_PVAL id="ddm_table_cols.arm10a004"></DD_ATTR_PVAL>
			<DD_ATTR_SLEV id="ddm_table_cols.arm10a004"></DD_ATTR_SLEV>
			<DD_ATTR_TABG id="ddm_table_cols.arm10a004"></DD_ATTR_TABG>
			<DD_ATTR_TIND id="ddm_table_cols.arm10a004">4</DD_ATTR_TIND>
			<DD_ATTR_HELP id="ddm_table_cols.arm10a004"></DD_ATTR_HELP>
			<SQL_COLUMN_NAME id="ddm_table_cols.arm10a004">V6_CODE_DESC</SQL_COLUMN_NAME>
			<DD_ATTR_FONT id="ddm_table_cols.arm10a004"></DD_ATTR_FONT>
			<DD_ATTR_STYL id="ddm_table_cols.arm10a004"></DD_ATTR_STYL>
			<DD_ATTR_FTSR id="ddm_table_cols.arm10a004">N</DD_ATTR_FTSR>
			<DD_ATTR_CWID id="ddm_table_cols.arm10a004"></DD_ATTR_CWID>
			<DD_ATTR_CTLI id="ddm_table_cols.arm10a004">3003</DD_ATTR_CTLI>
			<DD_ATTR_CTLN id="ddm_table_cols.arm10a004">ine_v6_code_desc</DD_ATTR_CTLN>
			<DD_ATTR_CTLC id="ddm_table_cols.arm10a004">0</DD_ATTR_CTLC>
			<DD_ATTR_RADG id="ddm_table_cols.arm10a004"></DD_ATTR_RADG>
			<DD_ATTR_RKEY id="ddm_table_cols.arm10a004">N</DD_ATTR_RKEY>
			<DD_ATTR_BTNS id="ddm_table_cols.arm10a004"></DD_ATTR_BTNS>
		</RECORD>
		<RECORD id="ddm_table_cols.arm10a005">
			<DD_TABLE_ALIAS id="ddm_table_cols.arm10a005">ARM10A          </DD_TABLE_ALIAS>
			<DD_SEQUENCE id="ddm_table_cols.arm10a005">005</DD_SEQUENCE>
			<DD_DATA_NAME id="ddm_table_cols.arm10a005">V6_PROX_OR_DAYS </DD_DATA_NAME>
			<DD_DVAR_NAME id="ddm_table_cols.arm10a005">V6_PROX_OR_DAYS </DD_DVAR_NAME>
			<DD_COL_REPEATS id="ddm_table_cols.arm10a005">0</DD_COL_REPEATS>
			<DD_COL_OCCURS id="ddm_table_cols.arm10a005">0</DD_COL_OCCURS>
			<DD_FIELD_DELIM id="ddm_table_cols.arm10a005">N</DD_FIELD_DELIM>
			<DD_DELIM_CHAR id="ddm_table_cols.arm10a005">0A</DD_DELIM_CHAR>
			<DD_SYSTEM_REC id="ddm_table_cols.arm10a005"></DD_SYSTEM_REC>
			<DD_SYSTEM_ID id="ddm_table_cols.arm10a005"></DD_SYSTEM_ID>
			<DD_MASK_TYPE id="ddm_table_cols.arm10a005"></DD_MASK_TYPE>
			<DD_CREATE_DATE id="ddm_table_cols.arm10a005">20161011</DD_CREATE_DATE>
			<DD_LSTREV_DATE id="ddm_table_cols.arm10a005">20161011</DD_LSTREV_DATE>
			<DD_ATTR_ABLC id="ddm_table_cols.arm10a005"></DD_ATTR_ABLC>
			<DD_ATTR_ABLV id="ddm_table_cols.arm10a005"></DD_ATTR_ABLV>
			<DD_ATTR_CPGM id="ddm_table_cols.arm10a005"></DD_ATTR_CPGM>
			<DD_ATTR_COLW id="ddm_table_cols.arm10a005">0</DD_ATTR_COLW>
			<DD_ATTR_CTLX id="ddm_table_cols.arm10a005"></DD_ATTR_CTLX>
			<DD_ATTR_CTLY id="ddm_table_cols.arm10a005"></DD_ATTR_CTLY>
			<DD_ATTR_CTLW id="ddm_table_cols.arm10a005"></DD_ATTR_CTLW>
			<DD_ATTR_CTLH id="ddm_table_cols.arm10a005"></DD_ATTR_CTLH>
			<DD_ATTR_DFLT id="ddm_table_cols.arm10a005"></DD_ATTR_DFLT>
			<DD_ATTR_DRLE id="ddm_table_cols.arm10a005"></DD_ATTR_DRLE>
			<DD_ATTR_GHDR id="ddm_table_cols.arm10a005"></DD_ATTR_GHDR>
			<DD_ATTR_IDEF id="ddm_table_cols.arm10a005"></DD_ATTR_IDEF>
			<DD_ATTR_LABL id="ddm_table_cols.arm10a005"></DD_ATTR_LABL>
			<DD_ATTR_LABS id="ddm_table_cols.arm10a005"></DD_ATTR_LABS>
			<DD_ATTR_MLAN id="ddm_table_cols.arm10a005">N</DD_ATTR_MLAN>
			<DD_ATTR_MINL id="ddm_table_cols.arm10a005"></DD_ATTR_MINL>
			<DD_ATTR_MAXL id="ddm_table_cols.arm10a005"></DD_ATTR_MAXL>
			<DD_ATTR_MINV id="ddm_table_cols.arm10a005"></DD_ATTR_MINV>
			<DD_ATTR_MAXV id="ddm_table_cols.arm10a005"></DD_ATTR_MAXV>
			<DD_ATTR_PROM id="ddm_table_cols.arm10a005"></DD_ATTR_PROM>
			<DD_ATTR_PVAL id="ddm_table_cols.arm10a005"></DD_ATTR_PVAL>
			<DD_ATTR_SLEV id="ddm_table_cols.arm10a005"></DD_ATTR_SLEV>
			<DD_ATTR_TABG id="ddm_table_cols.arm10a005"></DD_ATTR_TABG>
			<DD_ATTR_TIND id="ddm_table_cols.arm10a005">5</DD_ATTR_TIND>
			<DD_ATTR_HELP id="ddm_table_cols.arm10a005"></DD_ATTR_HELP>
			<SQL_COLUMN_NAME id="ddm_table_cols.arm10a005">V6_PROX_OR_DAYS</SQL_COLUMN_NAME>
			<DD_ATTR_FONT id="ddm_table_cols.arm10a005"></DD_ATTR_FONT>
			<DD_ATTR_STYL id="ddm_table_cols.arm10a005"></DD_ATTR_STYL>
			<DD_ATTR_FTSR id="ddm_table_cols.arm10a005">N</DD_ATTR_FTSR>
			<DD_ATTR_CWID id="ddm_table_cols.arm10a005"></DD_ATTR_CWID>
			<DD_ATTR_CTLI id="ddm_table_cols.arm10a005">3004</DD_ATTR_CTLI>
			<DD_ATTR_CTLN id="ddm_table_cols.arm10a005">ine_v6_prox_or_days</DD_ATTR_CTLN>
			<DD_ATTR_CTLC id="ddm_table_cols.arm10a005">0</DD_ATTR_CTLC>
			<DD_ATTR_RADG id="ddm_table_cols.arm10a005"></DD_ATTR_RADG>
			<DD_ATTR_RKEY id="ddm_table_cols.arm10a005">N</DD_ATTR_RKEY>
			<DD_ATTR_BTNS id="ddm_table_cols.arm10a005"></DD_ATTR_BTNS>
		</RECORD>
		<RECORD id="ddm_table_cols.arm10a006">
			<DD_TABLE_ALIAS id="ddm_table_cols.arm10a006">ARM10A          </DD_TABLE_ALIAS>
			<DD_SEQUENCE id="ddm_table_cols.arm10a006">006</DD_SEQUENCE>
			<DD_DATA_NAME id="ddm_table_cols.arm10a006">V6_CRED_HOLD    </DD_DATA_NAME>
			<DD_DVAR_NAME id="ddm_table_cols.arm10a006">V6_CRED_HOLD    </DD_DVAR_NAME>
			<DD_COL_REPEATS id="ddm_table_cols.arm10a006">0</DD_COL_REPEATS>
			<DD_COL_OCCURS id="ddm_table_cols.arm10a006">0</DD_COL_OCCURS>
			<DD_FIELD_DELIM id="ddm_table_cols.arm10a006">N</DD_FIELD_DELIM>
			<DD_DELIM_CHAR id="ddm_table_cols.arm10a006">0A</DD_DELIM_CHAR>
			<DD_SYSTEM_REC id="ddm_table_cols.arm10a006"></DD_SYSTEM_REC>
			<DD_SYSTEM_ID id="ddm_table_cols.arm10a006"></DD_SYSTEM_ID>
			<DD_MASK_TYPE id="ddm_table_cols.arm10a006"></DD_MASK_TYPE>
			<DD_CREATE_DATE id="ddm_table_cols.arm10a006">20161011</DD_CREATE_DATE>
			<DD_LSTREV_DATE id="ddm_table_cols.arm10a006">20161011</DD_LSTREV_DATE>
			<DD_ATTR_ABLC id="ddm_table_cols.arm10a006"></DD_ATTR_ABLC>
			<DD_ATTR_ABLV id="ddm_table_cols.arm10a006"></DD_ATTR_ABLV>
			<DD_ATTR_CPGM id="ddm_table_cols.arm10a006"></DD_ATTR_CPGM>
			<DD_ATTR_COLW id="ddm_table_cols.arm10a006">0</DD_ATTR_COLW>
			<DD_ATTR_CTLX id="ddm_table_cols.arm10a006"></DD_ATTR_CTLX>
			<DD_ATTR_CTLY id="ddm_table_cols.arm10a006"></DD_ATTR_CTLY>
			<DD_ATTR_CTLW id="ddm_table_cols.arm10a006"></DD_ATTR_CTLW>
			<DD_ATTR_CTLH id="ddm_table_cols.arm10a006"></DD_ATTR_CTLH>
			<DD_ATTR_DFLT id="ddm_table_cols.arm10a006"></DD_ATTR_DFLT>
			<DD_ATTR_DRLE id="ddm_table_cols.arm10a006"></DD_ATTR_DRLE>
			<DD_ATTR_GHDR id="ddm_table_cols.arm10a006"></DD_ATTR_GHDR>
			<DD_ATTR_IDEF id="ddm_table_cols.arm10a006"></DD_ATTR_IDEF>
			<DD_ATTR_LABL id="ddm_table_cols.arm10a006"></DD_ATTR_LABL>
			<DD_ATTR_LABS id="ddm_table_cols.arm10a006"></DD_ATTR_LABS>
			<DD_ATTR_MLAN id="ddm_table_cols.arm10a006">N</DD_ATTR_MLAN>
			<DD_ATTR_MINL id="ddm_table_cols.arm10a006"></DD_ATTR_MINL>
			<DD_ATTR_MAXL id="ddm_table_cols.arm10a006"></DD_ATTR_MAXL>
			<DD_ATTR_MINV id="ddm_table_cols.arm10a006"></DD_ATTR_MINV>
			<DD_ATTR_MAXV id="ddm_table_cols.arm10a006"></DD_ATTR_MAXV>
			<DD_ATTR_PROM id="ddm_table_cols.arm10a006"></DD_ATTR_PROM>
			<DD_ATTR_PVAL id="ddm_table_cols.arm10a006"></DD_ATTR_PVAL>
			<DD_ATTR_SLEV id="ddm_table_cols.arm10a006"></DD_ATTR_SLEV>
			<DD_ATTR_TABG id="ddm_table_cols.arm10a006"></DD_ATTR_TABG>
			<DD_ATTR_TIND id="ddm_table_cols.arm10a006">6</DD_ATTR_TIND>
			<DD_ATTR_HELP id="ddm_table_cols.arm10a006"></DD_ATTR_HELP>
			<SQL_COLUMN_NAME id="ddm_table_cols.arm10a006">V6_CRED_HOLD</SQL_COLUMN_NAME>
			<DD_ATTR_FONT id="ddm_table_cols.arm10a006"></DD_ATTR_FONT>
			<DD_ATTR_STYL id="ddm_table_cols.arm10a006"></DD_ATTR_STYL>
			<DD_ATTR_FTSR id="ddm_table_cols.arm10a006">N</DD_ATTR_FTSR>
			<DD_ATTR_CWID id="ddm_table_cols.arm10a006"></DD_ATTR_CWID>
			<DD_ATTR_CTLI id="ddm_table_cols.arm10a006">3005</DD_ATTR_CTLI>
			<DD_ATTR_CTLN id="ddm_table_cols.arm10a006">ine_v6_cred_hold</DD_ATTR_CTLN>
			<DD_ATTR_CTLC id="ddm_table_cols.arm10a006">0</DD_ATTR_CTLC>
			<DD_ATTR_RADG id="ddm_table_cols.arm10a006"></DD_ATTR_RADG>
			<DD_ATTR_RKEY id="ddm_table_cols.arm10a006">N</DD_ATTR_RKEY>
			<DD_ATTR_BTNS id="ddm_table_cols.arm10a006"></DD_ATTR_BTNS>
		</RECORD>
		<RECORD id="ddm_table_cols.arm10a007">
			<DD_TABLE_ALIAS id="ddm_table_cols.arm10a007">ARM10A          </DD_TABLE_ALIAS>
			<DD_SEQUENCE id="ddm_table_cols.arm10a007">007</DD_SEQUENCE>
			<DD_DATA_NAME id="ddm_table_cols.arm10a007">V6_RSRVD_STR    </DD_DATA_NAME>
			<DD_DVAR_NAME id="ddm_table_cols.arm10a007">V6_RSRVD_STR    </DD_DVAR_NAME>
			<DD_COL_REPEATS id="ddm_table_cols.arm10a007">3</DD_COL_REPEATS>
			<DD_COL_OCCURS id="ddm_table_cols.arm10a007">0</DD_COL_OCCURS>
			<DD_FIELD_DELIM id="ddm_table_cols.arm10a007">Y</DD_FIELD_DELIM>
			<DD_DELIM_CHAR id="ddm_table_cols.arm10a007">0A</DD_DELIM_CHAR>
			<DD_SYSTEM_REC id="ddm_table_cols.arm10a007"></DD_SYSTEM_REC>
			<DD_SYSTEM_ID id="ddm_table_cols.arm10a007"></DD_SYSTEM_ID>
			<DD_MASK_TYPE id="ddm_table_cols.arm10a007"></DD_MASK_TYPE>
			<DD_CREATE_DATE id="ddm_table_cols.arm10a007">20161011</DD_CREATE_DATE>
			<DD_LSTREV_DATE id="ddm_table_cols.arm10a007">20161011</DD_LSTREV_DATE>
			<DD_ATTR_ABLC id="ddm_table_cols.arm10a007"></DD_ATTR_ABLC>
			<DD_ATTR_ABLV id="ddm_table_cols.arm10a007"></DD_ATTR_ABLV>
			<DD_ATTR_CPGM id="ddm_table_cols.arm10a007"></DD_ATTR_CPGM>
			<DD_ATTR_COLW id="ddm_table_cols.arm10a007">0</DD_ATTR_COLW>
			<DD_ATTR_CTLX id="ddm_table_cols.arm10a007"></DD_ATTR_CTLX>
			<DD_ATTR_CTLY id="ddm_table_cols.arm10a007"></DD_ATTR_CTLY>
			<DD_ATTR_CTLW id="ddm_table_cols.arm10a007"></DD_ATTR_CTLW>
			<DD_ATTR_CTLH id="ddm_table_cols.arm10a007"></DD_ATTR_CTLH>
			<DD_ATTR_DFLT id="ddm_table_cols.arm10a007"></DD_ATTR_DFLT>
			<DD_ATTR_DRLE id="ddm_table_cols.arm10a007"></DD_ATTR_DRLE>
			<DD_ATTR_GHDR id="ddm_table_cols.arm10a007"></DD_ATTR_GHDR>
			<DD_ATTR_IDEF id="ddm_table_cols.arm10a007"></DD_ATTR_IDEF>
			<DD_ATTR_LABL id="ddm_table_cols.arm10a007"></DD_ATTR_LABL>
			<DD_ATTR_LABS id="ddm_table_cols.arm10a007"></DD_ATTR_LABS>
			<DD_ATTR_MLAN id="ddm_table_cols.arm10a007">N</DD_ATTR_MLAN>
			<DD_ATTR_MINL id="ddm_table_cols.arm10a007"></DD_ATTR_MINL>
			<DD_ATTR_MAXL id="ddm_table_cols.arm10a007"></DD_ATTR_MAXL>
			<DD_ATTR_MINV id="ddm_table_cols.arm10a007"></DD_ATTR_MINV>
			<DD_ATTR_MAXV id="ddm_table_cols.arm10a007"></DD_ATTR_MAXV>
			<DD_ATTR_PROM id="ddm_table_cols.arm10a007"></DD_ATTR_PROM>
			<DD_ATTR_PVAL id="ddm_table_cols.arm10a007"></DD_ATTR_PVAL>
			<DD_ATTR_SLEV id="ddm_table_cols.arm10a007"></DD_ATTR_SLEV>
			<DD_ATTR_TABG id="ddm_table_cols.arm10a007"></DD_ATTR_TABG>
			<DD_ATTR_TIND id="ddm_table_cols.arm10a007">7</DD_ATTR_TIND>
			<DD_ATTR_HELP id="ddm_table_cols.arm10a007"></DD_ATTR_HELP>
			<SQL_COLUMN_NAME id="ddm_table_cols.arm10a007">V6_RSRVD_STR</SQL_COLUMN_NAME>
			<DD_ATTR_FONT id="ddm_table_cols.arm10a007"></DD_ATTR_FONT>
			<DD_ATTR_STYL id="ddm_table_cols.arm10a007"></DD_ATTR_STYL>
			<DD_ATTR_FTSR id="ddm_table_cols.arm10a007">N</DD_ATTR_FTSR>
			<DD_ATTR_CWID id="ddm_table_cols.arm10a007"></DD_ATTR_CWID>
			<DD_ATTR_CTLI id="ddm_table_cols.arm10a007">3006</DD_ATTR_CTLI>
			<DD_ATTR_CTLN id="ddm_table_cols.arm10a007">ine_v6_rsrvd_str</DD_ATTR_CTLN>
			<DD_ATTR_CTLC id="ddm_table_cols.arm10a007">0</DD_ATTR_CTLC>
			<DD_ATTR_RADG id="ddm_table_cols.arm10a007"></DD_ATTR_RADG>
			<DD_ATTR_RKEY id="ddm_table_cols.arm10a007">N</DD_ATTR_RKEY>
			<DD_ATTR_BTNS id="ddm_table_cols.arm10a007"></DD_ATTR_BTNS>
		</RECORD>
		<RECORD id="ddm_table_cols.arm10a008">
			<DD_TABLE_ALIAS id="ddm_table_cols.arm10a008">ARM10A          </DD_TABLE_ALIAS>
			<DD_SEQUENCE id="ddm_table_cols.arm10a008">008</DD_SEQUENCE>
			<DD_DATA_NAME id="ddm_table_cols.arm10a008">V6_DISC_PERCENT </DD_DATA_NAME>
			<DD_DVAR_NAME id="ddm_table_cols.arm10a008">V6_DISC_PERCENT </DD_DVAR_NAME>
			<DD_COL_REPEATS id="ddm_table_cols.arm10a008">0</DD_COL_REPEATS>
			<DD_COL_OCCURS id="ddm_table_cols.arm10a008">0</DD_COL_OCCURS>
			<DD_FIELD_DELIM id="ddm_table_cols.arm10a008">Y</DD_FIELD_DELIM>
			<DD_DELIM_CHAR id="ddm_table_cols.arm10a008">0A</DD_DELIM_CHAR>
			<DD_SYSTEM_REC id="ddm_table_cols.arm10a008"></DD_SYSTEM_REC>
			<DD_SYSTEM_ID id="ddm_table_cols.arm10a008"></DD_SYSTEM_ID>
			<DD_MASK_TYPE id="ddm_table_cols.arm10a008"></DD_MASK_TYPE>
			<DD_CREATE_DATE id="ddm_table_cols.arm10a008">20161011</DD_CREATE_DATE>
			<DD_LSTREV_DATE id="ddm_table_cols.arm10a008">20161011</DD_LSTREV_DATE>
			<DD_ATTR_ABLC id="ddm_table_cols.arm10a008"></DD_ATTR_ABLC>
			<DD_ATTR_ABLV id="ddm_table_cols.arm10a008"></DD_ATTR_ABLV>
			<DD_ATTR_CPGM id="ddm_table_cols.arm10a008"></DD_ATTR_CPGM>
			<DD_ATTR_COLW id="ddm_table_cols.arm10a008">0</DD_ATTR_COLW>
			<DD_ATTR_CTLX id="ddm_table_cols.arm10a008"></DD_ATTR_CTLX>
			<DD_ATTR_CTLY id="ddm_table_cols.arm10a008"></DD_ATTR_CTLY>
			<DD_ATTR_CTLW id="ddm_table_cols.arm10a008"></DD_ATTR_CTLW>
			<DD_ATTR_CTLH id="ddm_table_cols.arm10a008"></DD_ATTR_CTLH>
			<DD_ATTR_DFLT id="ddm_table_cols.arm10a008"></DD_ATTR_DFLT>
			<DD_ATTR_DRLE id="ddm_table_cols.arm10a008"></DD_ATTR_DRLE>
			<DD_ATTR_GHDR id="ddm_table_cols.arm10a008"></DD_ATTR_GHDR>
			<DD_ATTR_IDEF id="ddm_table_cols.arm10a008"></DD_ATTR_IDEF>
			<DD_ATTR_LABL id="ddm_table_cols.arm10a008"></DD_ATTR_LABL>
			<DD_ATTR_LABS id="ddm_table_cols.arm10a008"></DD_ATTR_LABS>
			<DD_ATTR_MLAN id="ddm_table_cols.arm10a008">N</DD_ATTR_MLAN>
			<DD_ATTR_MINL id="ddm_table_cols.arm10a008"></DD_ATTR_MINL>
			<DD_ATTR_MAXL id="ddm_table_cols.arm10a008"></DD_ATTR_MAXL>
			<DD_ATTR_MINV id="ddm_table_cols.arm10a008"></DD_ATTR_MINV>
			<DD_ATTR_MAXV id="ddm_table_cols.arm10a008"></DD_ATTR_MAXV>
			<DD_ATTR_PROM id="ddm_table_cols.arm10a008"></DD_ATTR_PROM>
			<DD_ATTR_PVAL id="ddm_table_cols.arm10a008"></DD_ATTR_PVAL>
			<DD_ATTR_SLEV id="ddm_table_cols.arm10a008"></DD_ATTR_SLEV>
			<DD_ATTR_TABG id="ddm_table_cols.arm10a008"></DD_ATTR_TABG>
			<DD_ATTR_TIND id="ddm_table_cols.arm10a008">8</DD_ATTR_TIND>
			<DD_ATTR_HELP id="ddm_table_cols.arm10a008"></DD_ATTR_HELP>
			<SQL_COLUMN_NAME id="ddm_table_cols.arm10a008">V6_DISC_PERCENT</SQL_COLUMN_NAME>
			<DD_ATTR_FONT id="ddm_table_cols.arm10a008"></DD_ATTR_FONT>
			<DD_ATTR_STYL id="ddm_table_cols.arm10a008"></DD_ATTR_STYL>
			<DD_ATTR_FTSR id="ddm_table_cols.arm10a008">N</DD_ATTR_FTSR>
			<DD_ATTR_CWID id="ddm_table_cols.arm10a008"></DD_ATTR_CWID>
			<DD_ATTR_CTLI id="ddm_table_cols.arm10a008">3007</DD_ATTR_CTLI>
			<DD_ATTR_CTLN id="ddm_table_cols.arm10a008">inn_v6_disc_percent</DD_ATTR_CTLN>
			<DD_ATTR_CTLC id="ddm_table_cols.arm10a008">0</DD_ATTR_CTLC>
			<DD_ATTR_RADG id="ddm_table_cols.arm10a008"></DD_ATTR_RADG>
			<DD_ATTR_RKEY id="ddm_table_cols.arm10a008">N</DD_ATTR_RKEY>
			<DD_ATTR_BTNS id="ddm_table_cols.arm10a008"></DD_ATTR_BTNS>
		</RECORD>
		<RECORD id="ddm_table_cols.arm10a009">
			<DD_TABLE_ALIAS id="ddm_table_cols.arm10a009">ARM10A          </DD_TABLE_ALIAS>
			<DD_SEQUENCE id="ddm_table_cols.arm10a009">009</DD_SEQUENCE>
			<DD_DATA_NAME id="ddm_table_cols.arm10a009">V6_INV_DAYS_DUE </DD_DATA_NAME>
			<DD_DVAR_NAME id="ddm_table_cols.arm10a009">V6_INV_DAYS_DUE </DD_DVAR_NAME>
			<DD_COL_REPEATS id="ddm_table_cols.arm10a009">0</DD_COL_REPEATS>
			<DD_COL_OCCURS id="ddm_table_cols.arm10a009">0</DD_COL_OCCURS>
			<DD_FIELD_DELIM id="ddm_table_cols.arm10a009">Y</DD_FIELD_DELIM>
			<DD_DELIM_CHAR id="ddm_table_cols.arm10a009">0A</DD_DELIM_CHAR>
			<DD_SYSTEM_REC id="ddm_table_cols.arm10a009"></DD_SYSTEM_REC>
			<DD_SYSTEM_ID id="ddm_table_cols.arm10a009"></DD_SYSTEM_ID>
			<DD_MASK_TYPE id="ddm_table_cols.arm10a009"></DD_MASK_TYPE>
			<DD_CREATE_DATE id="ddm_table_cols.arm10a009">20161011</DD_CREATE_DATE>
			<DD_LSTREV_DATE id="ddm_table_cols.arm10a009">20161011</DD_LSTREV_DATE>
			<DD_ATTR_ABLC id="ddm_table_cols.arm10a009"></DD_ATTR_ABLC>
			<DD_ATTR_ABLV id="ddm_table_cols.arm10a009"></DD_ATTR_ABLV>
			<DD_ATTR_CPGM id="ddm_table_cols.arm10a009"></DD_ATTR_CPGM>
			<DD_ATTR_COLW id="ddm_table_cols.arm10a009">0</DD_ATTR_COLW>
			<DD_ATTR_CTLX id="ddm_table_cols.arm10a009"></DD_ATTR_CTLX>
			<DD_ATTR_CTLY id="ddm_table_cols.arm10a009"></DD_ATTR_CTLY>
			<DD_ATTR_CTLW id="ddm_table_cols.arm10a009"></DD_ATTR_CTLW>
			<DD_ATTR_CTLH id="ddm_table_cols.arm10a009"></DD_ATTR_CTLH>
			<DD_ATTR_DFLT id="ddm_table_cols.arm10a009"></DD_ATTR_DFLT>
			<DD_ATTR_DRLE id="ddm_table_cols.arm10a009"></DD_ATTR_DRLE>
			<DD_ATTR_GHDR id="ddm_table_cols.arm10a009"></DD_ATTR_GHDR>
			<DD_ATTR_IDEF id="ddm_table_cols.arm10a009"></DD_ATTR_IDEF>
			<DD_ATTR_LABL id="ddm_table_cols.arm10a009"></DD_ATTR_LABL>
			<DD_ATTR_LABS id="ddm_table_cols.arm10a009"></DD_ATTR_LABS>
			<DD_ATTR_MLAN id="ddm_table_cols.arm10a009">N</DD_ATTR_MLAN>
			<DD_ATTR_MINL id="ddm_table_cols.arm10a009"></DD_ATTR_MINL>
			<DD_ATTR_MAXL id="ddm_table_cols.arm10a009"></DD_ATTR_MAXL>
			<DD_ATTR_MINV id="ddm_table_cols.arm10a009"></DD_ATTR_MINV>
			<DD_ATTR_MAXV id="ddm_table_cols.arm10a009"></DD_ATTR_MAXV>
			<DD_ATTR_PROM id="ddm_table_cols.arm10a009"></DD_ATTR_PROM>
			<DD_ATTR_PVAL id="ddm_table_cols.arm10a009"></DD_ATTR_PVAL>
			<DD_ATTR_SLEV id="ddm_table_cols.arm10a009"></DD_ATTR_SLEV>
			<DD_ATTR_TABG id="ddm_table_cols.arm10a009"></DD_ATTR_TABG>
			<DD_ATTR_TIND id="ddm_table_cols.arm10a009">9</DD_ATTR_TIND>
			<DD_ATTR_HELP id="ddm_table_cols.arm10a009"></DD_ATTR_HELP>
			<SQL_COLUMN_NAME id="ddm_table_cols.arm10a009">V6_INV_DAYS_DUE</SQL_COLUMN_NAME>
			<DD_ATTR_FONT id="ddm_table_cols.arm10a009"></DD_ATTR_FONT>
			<DD_ATTR_STYL id="ddm_table_cols.arm10a009"></DD_ATTR_STYL>
			<DD_ATTR_FTSR id="ddm_table_cols.arm10a009">N</DD_ATTR_FTSR>
			<DD_ATTR_CWID id="ddm_table_cols.arm10a009"></DD_ATTR_CWID>
			<DD_ATTR_CTLI id="ddm_table_cols.arm10a009">3008</DD_ATTR_CTLI>
			<DD_ATTR_CTLN id="ddm_table_cols.arm10a009">inn_v6_inv_days_due</DD_ATTR_CTLN>
			<DD_ATTR_CTLC id="ddm_table_cols.arm10a009">0</DD_ATTR_CTLC>
			<DD_ATTR_RADG id="ddm_table_cols.arm10a009"></DD_ATTR_RADG>
			<DD_ATTR_RKEY id="ddm_table_cols.arm10a009">N</DD_ATTR_RKEY>
			<DD_ATTR_BTNS id="ddm_table_cols.arm10a009"></DD_ATTR_BTNS>
		</RECORD>
		<RECORD id="ddm_table_cols.arm10a010">
			<DD_TABLE_ALIAS id="ddm_table_cols.arm10a010">ARM10A          </DD_TABLE_ALIAS>
			<DD_SEQUENCE id="ddm_table_cols.arm10a010">010</DD_SEQUENCE>
			<DD_DATA_NAME id="ddm_table_cols.arm10a010">V6_DISC_DAYS    </DD_DATA_NAME>
			<DD_DVAR_NAME id="ddm_table_cols.arm10a010">V6_DISC_DAYS    </DD_DVAR_NAME>
			<DD_COL_REPEATS id="ddm_table_cols.arm10a010">0</DD_COL_REPEATS>
			<DD_COL_OCCURS id="ddm_table_cols.arm10a010">0</DD_COL_OCCURS>
			<DD_FIELD_DELIM id="ddm_table_cols.arm10a010">Y</DD_FIELD_DELIM>
			<DD_DELIM_CHAR id="ddm_table_cols.arm10a010">0A</DD_DELIM_CHAR>
			<DD_SYSTEM_REC id="ddm_table_cols.arm10a010"></DD_SYSTEM_REC>
			<DD_SYSTEM_ID id="ddm_table_cols.arm10a010"></DD_SYSTEM_ID>
			<DD_MASK_TYPE id="ddm_table_cols.arm10a010"></DD_MASK_TYPE>
			<DD_CREATE_DATE id="ddm_table_cols.arm10a010">20161011</DD_CREATE_DATE>
			<DD_LSTREV_DATE id="ddm_table_cols.arm10a010">20161011</DD_LSTREV_DATE>
			<DD_ATTR_ABLC id="ddm_table_cols.arm10a010"></DD_ATTR_ABLC>
			<DD_ATTR_ABLV id="ddm_table_cols.arm10a010"></DD_ATTR_ABLV>
			<DD_ATTR_CPGM id="ddm_table_cols.arm10a010"></DD_ATTR_CPGM>
			<DD_ATTR_COLW id="ddm_table_cols.arm10a010">0</DD_ATTR_COLW>
			<DD_ATTR_CTLX id="ddm_table_cols.arm10a010"></DD_ATTR_CTLX>
			<DD_ATTR_CTLY id="ddm_table_cols.arm10a010"></DD_ATTR_CTLY>
			<DD_ATTR_CTLW id="ddm_table_cols.arm10a010"></DD_ATTR_CTLW>
			<DD_ATTR_CTLH id="ddm_table_cols.arm10a010"></DD_ATTR_CTLH>
			<DD_ATTR_DFLT id="ddm_table_cols.arm10a010"></DD_ATTR_DFLT>
			<DD_ATTR_DRLE id="ddm_table_cols.arm10a010"></DD_ATTR_DRLE>
			<DD_ATTR_GHDR id="ddm_table_cols.arm10a010"></DD_ATTR_GHDR>
			<DD_ATTR_IDEF id="ddm_table_cols.arm10a010"></DD_ATTR_IDEF>
			<DD_ATTR_LABL id="ddm_table_cols.arm10a010"></DD_ATTR_LABL>
			<DD_ATTR_LABS id="ddm_table_cols.arm10a010"></DD_ATTR_LABS>
			<DD_ATTR_MLAN id="ddm_table_cols.arm10a010">N</DD_ATTR_MLAN>
			<DD_ATTR_MINL id="ddm_table_cols.arm10a010"></DD_ATTR_MINL>
			<DD_ATTR_MAXL id="ddm_table_cols.arm10a010"></DD_ATTR_MAXL>
			<DD_ATTR_MINV id="ddm_table_cols.arm10a010"></DD_ATTR_MINV>
			<DD_ATTR_MAXV id="ddm_table_cols.arm10a010"></DD_ATTR_MAXV>
			<DD_ATTR_PROM id="ddm_table_cols.arm10a010"></DD_ATTR_PROM>
			<DD_ATTR_PVAL id="ddm_table_cols.arm10a010"></DD_ATTR_PVAL>
			<DD_ATTR_SLEV id="ddm_table_cols.arm10a010"></DD_ATTR_SLEV>
			<DD_ATTR_TABG id="ddm_table_cols.arm10a010"></DD_ATTR_TABG>
			<DD_ATTR_TIND id="ddm_table_cols.arm10a010">10</DD_ATTR_TIND>
			<DD_ATTR_HELP id="ddm_table_cols.arm10a010"></DD_ATTR_HELP>
			<SQL_COLUMN_NAME id="ddm_table_cols.arm10a010">V6_DISC_DAYS</SQL_COLUMN_NAME>
			<DD_ATTR_FONT id="ddm_table_cols.arm10a010"></DD_ATTR_FONT>
			<DD_ATTR_STYL id="ddm_table_cols.arm10a010"></DD_ATTR_STYL>
			<DD_ATTR_FTSR id="ddm_table_cols.arm10a010">N</DD_ATTR_FTSR>
			<DD_ATTR_CWID id="ddm_table_cols.arm10a010"></DD_ATTR_CWID>
			<DD_ATTR_CTLI id="ddm_table_cols.arm10a010">3009</DD_ATTR_CTLI>
			<DD_ATTR_CTLN id="ddm_table_cols.arm10a010">inn_v6_disc_days</DD_ATTR_CTLN>
			<DD_ATTR_CTLC id="ddm_table_cols.arm10a010">0</DD_ATTR_CTLC>
			<DD_ATTR_RADG id="ddm_table_cols.arm10a010"></DD_ATTR_RADG>
			<DD_ATTR_RKEY id="ddm_table_cols.arm10a010">N</DD_ATTR_RKEY>
			<DD_ATTR_BTNS id="ddm_table_cols.arm10a010"></DD_ATTR_BTNS>
		</RECORD>
	</ALIAS>
	<ALIAS id="ddm_elements">
		<ID id="ddm_elements">DDM_ELEMENTS</ID>
		<RECORD id="ddm_elements.v6_firm_id">
			<DD_DATA_NAME id="ddm_elements.v6_firm_id">V6_FIRM_ID      </DD_DATA_NAME>
			<DD_DESCRIPTION id="ddm_elements.v6_firm_id">V6 Firm Id</DD_DESCRIPTION>
			<DD_DATA_TYPE id="ddm_elements.v6_firm_id">C</DD_DATA_TYPE>
			<DD_DATA_LENGTH id="ddm_elements.v6_firm_id">2</DD_DATA_LENGTH>
			<DD_MASK_TYPE id="ddm_elements.v6_firm_id"></DD_MASK_TYPE>
			<DD_SYSTEM_REC id="ddm_elements.v6_firm_id"></DD_SYSTEM_REC>
			<ASC_COMP_ID id="ddm_elements.v6_firm_id">00000000</ASC_COMP_ID>
			<ASC_PROD_ID id="ddm_elements.v6_firm_id">V6H</ASC_PROD_ID>
			<LOCALIZATION_EX id="ddm_elements.v6_firm_id"></LOCALIZATION_EX>
			<DD_CREATE_DATE id="ddm_elements.v6_firm_id">20160826</DD_CREATE_DATE>
			<DD_LSTREV_DATE id="ddm_elements.v6_firm_id">20160831</DD_LSTREV_DATE>
			<DD_AUTO_COMP id="ddm_elements.v6_firm_id"></DD_AUTO_COMP>
			<DD_ATTR_BLNK id="ddm_elements.v6_firm_id"></DD_ATTR_BLNK>
			<DD_ATTR_CDAT id="ddm_elements.v6_firm_id"></DD_ATTR_CDAT>
			<DD_ATTR_CTLW id="ddm_elements.v6_firm_id"></DD_ATTR_CTLW>
			<DD_ATTR_CTLH id="ddm_elements.v6_firm_id"></DD_ATTR_CTLH>
			<DD_ATTR_CTYP id="ddm_elements.v6_firm_id">H</DD_ATTR_CTYP>
			<DD_ATTR_DCOL id="ddm_elements.v6_firm_id"></DD_ATTR_DCOL>
			<DD_ATTR_DCOM id="ddm_elements.v6_firm_id"></DD_ATTR_DCOM>
			<DD_ATTR_DEXP id="ddm_elements.v6_firm_id"></DD_ATTR_DEXP>
			<DD_ATTR_DFLT id="ddm_elements.v6_firm_id"></DD_ATTR_DFLT>
			<DD_ATTR_DKNM id="ddm_elements.v6_firm_id"></DD_ATTR_DKNM>
			<DD_ATTR_DKEY id="ddm_elements.v6_firm_id"></DD_ATTR_DKEY>
			<DD_ATTR_DTAB id="ddm_elements.v6_firm_id"></DD_ATTR_DTAB>
			<DD_ATTR_DINQ id="ddm_elements.v6_firm_id"></DD_ATTR_DINQ>
			<DD_ATTR_ENCR id="ddm_elements.v6_firm_id"></DD_ATTR_ENCR>
			<DD_ATTR_IDEF id="ddm_elements.v6_firm_id"></DD_ATTR_IDEF>
			<DD_ATTR_LABL id="ddm_elements.v6_firm_id">V6 Firm Id</DD_ATTR_LABL>
			<DD_ATTR_LABS id="ddm_elements.v6_firm_id">V6 Firm Id</DD_ATTR_LABS>
			<DD_ATTR_LDIS id="ddm_elements.v6_firm_id"></DD_ATTR_LDIS>
			<DD_ATTR_MAXL id="ddm_elements.v6_firm_id"></DD_ATTR_MAXL>
			<DD_ATTR_MAXR id="ddm_elements.v6_firm_id"></DD_ATTR_MAXR>
			<DD_ATTR_MAXV id="ddm_elements.v6_firm_id"></DD_ATTR_MAXV>
			<DD_ATTR_MINL id="ddm_elements.v6_firm_id"></DD_ATTR_MINL>
			<DD_ATTR_MINV id="ddm_elements.v6_firm_id"></DD_ATTR_MINV>
			<DD_ATTR_MSKI id="ddm_elements.v6_firm_id"></DD_ATTR_MSKI>
			<DD_ATTR_MSKO id="ddm_elements.v6_firm_id"></DD_ATTR_MSKO>
			<DD_ATTR_PADC id="ddm_elements.v6_firm_id"></DD_ATTR_PADC>
			<DD_ATTR_PADJ id="ddm_elements.v6_firm_id"></DD_ATTR_PADJ>
			<DD_ATTR_PREC id="ddm_elements.v6_firm_id">0</DD_ATTR_PREC>
			<DD_ATTR_PROM id="ddm_elements.v6_firm_id"></DD_ATTR_PROM>
			<DD_ATTR_PVAL id="ddm_elements.v6_firm_id">stbl("+FIRM_ID")</DD_ATTR_PVAL>
			<DD_ATTR_SDLG id="ddm_elements.v6_firm_id"></DD_ATTR_SDLG>
			<DD_ATTR_SLEV id="ddm_elements.v6_firm_id"></DD_ATTR_SLEV>
			<DD_ATTR_STYP id="ddm_elements.v6_firm_id"></DD_ATTR_STYP>
			<DD_ATTR_STEP id="ddm_elements.v6_firm_id">0</DD_ATTR_STEP>
			<DD_ATTR_FLPT id="ddm_elements.v6_firm_id"></DD_ATTR_FLPT>
			<DD_ATTR_OEMD id="ddm_elements.v6_firm_id"></DD_ATTR_OEMD>
			<DD_ATTR_Y2KW id="ddm_elements.v6_firm_id"></DD_ATTR_Y2KW>
			<DD_ATTR_CASB id="ddm_elements.v6_firm_id"></DD_ATTR_CASB>
		</RECORD>
		<RECORD id="ddm_elements.v6_record_id_a">
			<DD_DATA_NAME id="ddm_elements.v6_record_id_a">V6_RECORD_ID_A  </DD_DATA_NAME>
			<DD_DESCRIPTION id="ddm_elements.v6_record_id_a">V6 Record Id A</DD_DESCRIPTION>
			<DD_DATA_TYPE id="ddm_elements.v6_record_id_a">C</DD_DATA_TYPE>
			<DD_DATA_LENGTH id="ddm_elements.v6_record_id_a">1</DD_DATA_LENGTH>
			<DD_MASK_TYPE id="ddm_elements.v6_record_id_a"></DD_MASK_TYPE>
			<DD_SYSTEM_REC id="ddm_elements.v6_record_id_a"></DD_SYSTEM_REC>
			<ASC_COMP_ID id="ddm_elements.v6_record_id_a">00000000</ASC_COMP_ID>
			<ASC_PROD_ID id="ddm_elements.v6_record_id_a">V6H</ASC_PROD_ID>
			<LOCALIZATION_EX id="ddm_elements.v6_record_id_a"></LOCALIZATION_EX>
			<DD_CREATE_DATE id="ddm_elements.v6_record_id_a">2457632</DD_CREATE_DATE>
			<DD_LSTREV_DATE id="ddm_elements.v6_record_id_a">20160831</DD_LSTREV_DATE>
			<DD_AUTO_COMP id="ddm_elements.v6_record_id_a"></DD_AUTO_COMP>
			<DD_ATTR_BLNK id="ddm_elements.v6_record_id_a"></DD_ATTR_BLNK>
			<DD_ATTR_CDAT id="ddm_elements.v6_record_id_a"></DD_ATTR_CDAT>
			<DD_ATTR_CTLW id="ddm_elements.v6_record_id_a"></DD_ATTR_CTLW>
			<DD_ATTR_CTLH id="ddm_elements.v6_record_id_a"></DD_ATTR_CTLH>
			<DD_ATTR_CTYP id="ddm_elements.v6_record_id_a">E</DD_ATTR_CTYP>
			<DD_ATTR_DCOL id="ddm_elements.v6_record_id_a"></DD_ATTR_DCOL>
			<DD_ATTR_DCOM id="ddm_elements.v6_record_id_a"></DD_ATTR_DCOM>
			<DD_ATTR_DEXP id="ddm_elements.v6_record_id_a"></DD_ATTR_DEXP>
			<DD_ATTR_DFLT id="ddm_elements.v6_record_id_a"></DD_ATTR_DFLT>
			<DD_ATTR_DKNM id="ddm_elements.v6_record_id_a"></DD_ATTR_DKNM>
			<DD_ATTR_DKEY id="ddm_elements.v6_record_id_a"></DD_ATTR_DKEY>
			<DD_ATTR_DTAB id="ddm_elements.v6_record_id_a"></DD_ATTR_DTAB>
			<DD_ATTR_DINQ id="ddm_elements.v6_record_id_a"></DD_ATTR_DINQ>
			<DD_ATTR_ENCR id="ddm_elements.v6_record_id_a"></DD_ATTR_ENCR>
			<DD_ATTR_IDEF id="ddm_elements.v6_record_id_a"></DD_ATTR_IDEF>
			<DD_ATTR_LABL id="ddm_elements.v6_record_id_a">V6 Record Id A</DD_ATTR_LABL>
			<DD_ATTR_LABS id="ddm_elements.v6_record_id_a">V6 Record Id A</DD_ATTR_LABS>
			<DD_ATTR_LDIS id="ddm_elements.v6_record_id_a"></DD_ATTR_LDIS>
			<DD_ATTR_MAXL id="ddm_elements.v6_record_id_a"></DD_ATTR_MAXL>
			<DD_ATTR_MAXR id="ddm_elements.v6_record_id_a"></DD_ATTR_MAXR>
			<DD_ATTR_MAXV id="ddm_elements.v6_record_id_a"></DD_ATTR_MAXV>
			<DD_ATTR_MINL id="ddm_elements.v6_record_id_a"></DD_ATTR_MINL>
			<DD_ATTR_MINV id="ddm_elements.v6_record_id_a"></DD_ATTR_MINV>
			<DD_ATTR_MSKI id="ddm_elements.v6_record_id_a"></DD_ATTR_MSKI>
			<DD_ATTR_MSKO id="ddm_elements.v6_record_id_a"></DD_ATTR_MSKO>
			<DD_ATTR_PADC id="ddm_elements.v6_record_id_a"></DD_ATTR_PADC>
			<DD_ATTR_PADJ id="ddm_elements.v6_record_id_a"></DD_ATTR_PADJ>
			<DD_ATTR_PREC id="ddm_elements.v6_record_id_a">0</DD_ATTR_PREC>
			<DD_ATTR_PROM id="ddm_elements.v6_record_id_a"></DD_ATTR_PROM>
			<DD_ATTR_PVAL id="ddm_elements.v6_record_id_a"></DD_ATTR_PVAL>
			<DD_ATTR_SDLG id="ddm_elements.v6_record_id_a"></DD_ATTR_SDLG>
			<DD_ATTR_SLEV id="ddm_elements.v6_record_id_a"></DD_ATTR_SLEV>
			<DD_ATTR_STYP id="ddm_elements.v6_record_id_a"></DD_ATTR_STYP>
			<DD_ATTR_STEP id="ddm_elements.v6_record_id_a">0</DD_ATTR_STEP>
			<DD_ATTR_FLPT id="ddm_elements.v6_record_id_a"></DD_ATTR_FLPT>
			<DD_ATTR_OEMD id="ddm_elements.v6_record_id_a"></DD_ATTR_OEMD>
			<DD_ATTR_Y2KW id="ddm_elements.v6_record_id_a"></DD_ATTR_Y2KW>
			<DD_ATTR_CASB id="ddm_elements.v6_record_id_a"></DD_ATTR_CASB>
		</RECORD>
		<RECORD id="ddm_elements.v6_terms_code">
			<DD_DATA_NAME id="ddm_elements.v6_terms_code">V6_TERMS_CODE   </DD_DATA_NAME>
			<DD_DESCRIPTION id="ddm_elements.v6_terms_code">V6 Terms Code</DD_DESCRIPTION>
			<DD_DATA_TYPE id="ddm_elements.v6_terms_code">C</DD_DATA_TYPE>
			<DD_DATA_LENGTH id="ddm_elements.v6_terms_code">2</DD_DATA_LENGTH>
			<DD_MASK_TYPE id="ddm_elements.v6_terms_code"></DD_MASK_TYPE>
			<DD_SYSTEM_REC id="ddm_elements.v6_terms_code"></DD_SYSTEM_REC>
			<ASC_COMP_ID id="ddm_elements.v6_terms_code">00000000</ASC_COMP_ID>
			<ASC_PROD_ID id="ddm_elements.v6_terms_code">V6H</ASC_PROD_ID>
			<LOCALIZATION_EX id="ddm_elements.v6_terms_code"></LOCALIZATION_EX>
			<DD_CREATE_DATE id="ddm_elements.v6_terms_code">20160819</DD_CREATE_DATE>
			<DD_LSTREV_DATE id="ddm_elements.v6_terms_code">20160819</DD_LSTREV_DATE>
			<DD_AUTO_COMP id="ddm_elements.v6_terms_code"></DD_AUTO_COMP>
			<DD_ATTR_BLNK id="ddm_elements.v6_terms_code"></DD_ATTR_BLNK>
			<DD_ATTR_CDAT id="ddm_elements.v6_terms_code"></DD_ATTR_CDAT>
			<DD_ATTR_CTLW id="ddm_elements.v6_terms_code"></DD_ATTR_CTLW>
			<DD_ATTR_CTLH id="ddm_elements.v6_terms_code"></DD_ATTR_CTLH>
			<DD_ATTR_CTYP id="ddm_elements.v6_terms_code">E</DD_ATTR_CTYP>
			<DD_ATTR_DCOL id="ddm_elements.v6_terms_code"></DD_ATTR_DCOL>
			<DD_ATTR_DCOM id="ddm_elements.v6_terms_code"></DD_ATTR_DCOM>
			<DD_ATTR_DEXP id="ddm_elements.v6_terms_code"></DD_ATTR_DEXP>
			<DD_ATTR_DFLT id="ddm_elements.v6_terms_code"></DD_ATTR_DFLT>
			<DD_ATTR_DKNM id="ddm_elements.v6_terms_code"></DD_ATTR_DKNM>
			<DD_ATTR_DKEY id="ddm_elements.v6_terms_code"></DD_ATTR_DKEY>
			<DD_ATTR_DTAB id="ddm_elements.v6_terms_code"></DD_ATTR_DTAB>
			<DD_ATTR_DINQ id="ddm_elements.v6_terms_code"></DD_ATTR_DINQ>
			<DD_ATTR_ENCR id="ddm_elements.v6_terms_code"></DD_ATTR_ENCR>
			<DD_ATTR_IDEF id="ddm_elements.v6_terms_code"></DD_ATTR_IDEF>
			<DD_ATTR_LABL id="ddm_elements.v6_terms_code">V6 Terms Code</DD_ATTR_LABL>
			<DD_ATTR_LABS id="ddm_elements.v6_terms_code">V6 Terms Code</DD_ATTR_LABS>
			<DD_ATTR_LDIS id="ddm_elements.v6_terms_code"></DD_ATTR_LDIS>
			<DD_ATTR_MAXL id="ddm_elements.v6_terms_code"></DD_ATTR_MAXL>
			<DD_ATTR_MAXR id="ddm_elements.v6_terms_code"></DD_ATTR_MAXR>
			<DD_ATTR_MAXV id="ddm_elements.v6_terms_code"></DD_ATTR_MAXV>
			<DD_ATTR_MINL id="ddm_elements.v6_terms_code"></DD_ATTR_MINL>
			<DD_ATTR_MINV id="ddm_elements.v6_terms_code"></DD_ATTR_MINV>
			<DD_ATTR_MSKI id="ddm_elements.v6_terms_code"></DD_ATTR_MSKI>
			<DD_ATTR_MSKO id="ddm_elements.v6_terms_code"></DD_ATTR_MSKO>
			<DD_ATTR_PADC id="ddm_elements.v6_terms_code"></DD_ATTR_PADC>
			<DD_ATTR_PADJ id="ddm_elements.v6_terms_code"></DD_ATTR_PADJ>
			<DD_ATTR_PREC id="ddm_elements.v6_terms_code">0</DD_ATTR_PREC>
			<DD_ATTR_PROM id="ddm_elements.v6_terms_code"></DD_ATTR_PROM>
			<DD_ATTR_PVAL id="ddm_elements.v6_terms_code"></DD_ATTR_PVAL>
			<DD_ATTR_SDLG id="ddm_elements.v6_terms_code"></DD_ATTR_SDLG>
			<DD_ATTR_SLEV id="ddm_elements.v6_terms_code"></DD_ATTR_SLEV>
			<DD_ATTR_STYP id="ddm_elements.v6_terms_code"></DD_ATTR_STYP>
			<DD_ATTR_STEP id="ddm_elements.v6_terms_code"></DD_ATTR_STEP>
			<DD_ATTR_FLPT id="ddm_elements.v6_terms_code"></DD_ATTR_FLPT>
			<DD_ATTR_OEMD id="ddm_elements.v6_terms_code"></DD_ATTR_OEMD>
			<DD_ATTR_Y2KW id="ddm_elements.v6_terms_code"></DD_ATTR_Y2KW>
			<DD_ATTR_CASB id="ddm_elements.v6_terms_code"></DD_ATTR_CASB>
		</RECORD>
		<RECORD id="ddm_elements.v6_code_desc">
			<DD_DATA_NAME id="ddm_elements.v6_code_desc">V6_CODE_DESC    </DD_DATA_NAME>
			<DD_DESCRIPTION id="ddm_elements.v6_code_desc">V6 Code Desc</DD_DESCRIPTION>
			<DD_DATA_TYPE id="ddm_elements.v6_code_desc">C</DD_DATA_TYPE>
			<DD_DATA_LENGTH id="ddm_elements.v6_code_desc">20</DD_DATA_LENGTH>
			<DD_MASK_TYPE id="ddm_elements.v6_code_desc"></DD_MASK_TYPE>
			<DD_SYSTEM_REC id="ddm_elements.v6_code_desc"></DD_SYSTEM_REC>
			<ASC_COMP_ID id="ddm_elements.v6_code_desc">00000000</ASC_COMP_ID>
			<ASC_PROD_ID id="ddm_elements.v6_code_desc">V6H</ASC_PROD_ID>
			<LOCALIZATION_EX id="ddm_elements.v6_code_desc"></LOCALIZATION_EX>
			<DD_CREATE_DATE id="ddm_elements.v6_code_desc">20160819</DD_CREATE_DATE>
			<DD_LSTREV_DATE id="ddm_elements.v6_code_desc">20160819</DD_LSTREV_DATE>
			<DD_AUTO_COMP id="ddm_elements.v6_code_desc"></DD_AUTO_COMP>
			<DD_ATTR_BLNK id="ddm_elements.v6_code_desc"></DD_ATTR_BLNK>
			<DD_ATTR_CDAT id="ddm_elements.v6_code_desc"></DD_ATTR_CDAT>
			<DD_ATTR_CTLW id="ddm_elements.v6_code_desc"></DD_ATTR_CTLW>
			<DD_ATTR_CTLH id="ddm_elements.v6_code_desc"></DD_ATTR_CTLH>
			<DD_ATTR_CTYP id="ddm_elements.v6_code_desc">E</DD_ATTR_CTYP>
			<DD_ATTR_DCOL id="ddm_elements.v6_code_desc"></DD_ATTR_DCOL>
			<DD_ATTR_DCOM id="ddm_elements.v6_code_desc"></DD_ATTR_DCOM>
			<DD_ATTR_DEXP id="ddm_elements.v6_code_desc"></DD_ATTR_DEXP>
			<DD_ATTR_DFLT id="ddm_elements.v6_code_desc"></DD_ATTR_DFLT>
			<DD_ATTR_DKNM id="ddm_elements.v6_code_desc"></DD_ATTR_DKNM>
			<DD_ATTR_DKEY id="ddm_elements.v6_code_desc"></DD_ATTR_DKEY>
			<DD_ATTR_DTAB id="ddm_elements.v6_code_desc"></DD_ATTR_DTAB>
			<DD_ATTR_DINQ id="ddm_elements.v6_code_desc"></DD_ATTR_DINQ>
			<DD_ATTR_ENCR id="ddm_elements.v6_code_desc"></DD_ATTR_ENCR>
			<DD_ATTR_IDEF id="ddm_elements.v6_code_desc"></DD_ATTR_IDEF>
			<DD_ATTR_LABL id="ddm_elements.v6_code_desc">V6 Code Desc</DD_ATTR_LABL>
			<DD_ATTR_LABS id="ddm_elements.v6_code_desc">V6 Code Desc</DD_ATTR_LABS>
			<DD_ATTR_LDIS id="ddm_elements.v6_code_desc"></DD_ATTR_LDIS>
			<DD_ATTR_MAXL id="ddm_elements.v6_code_desc"></DD_ATTR_MAXL>
			<DD_ATTR_MAXR id="ddm_elements.v6_code_desc"></DD_ATTR_MAXR>
			<DD_ATTR_MAXV id="ddm_elements.v6_code_desc"></DD_ATTR_MAXV>
			<DD_ATTR_MINL id="ddm_elements.v6_code_desc"></DD_ATTR_MINL>
			<DD_ATTR_MINV id="ddm_elements.v6_code_desc"></DD_ATTR_MINV>
			<DD_ATTR_MSKI id="ddm_elements.v6_code_desc"></DD_ATTR_MSKI>
			<DD_ATTR_MSKO id="ddm_elements.v6_code_desc"></DD_ATTR_MSKO>
			<DD_ATTR_PADC id="ddm_elements.v6_code_desc"></DD_ATTR_PADC>
			<DD_ATTR_PADJ id="ddm_elements.v6_code_desc"></DD_ATTR_PADJ>
			<DD_ATTR_PREC id="ddm_elements.v6_code_desc">0</DD_ATTR_PREC>
			<DD_ATTR_PROM id="ddm_elements.v6_code_desc"></DD_ATTR_PROM>
			<DD_ATTR_PVAL id="ddm_elements.v6_code_desc"></DD_ATTR_PVAL>
			<DD_ATTR_SDLG id="ddm_elements.v6_code_desc"></DD_ATTR_SDLG>
			<DD_ATTR_SLEV id="ddm_elements.v6_code_desc"></DD_ATTR_SLEV>
			<DD_ATTR_STYP id="ddm_elements.v6_code_desc"></DD_ATTR_STYP>
			<DD_ATTR_STEP id="ddm_elements.v6_code_desc"></DD_ATTR_STEP>
			<DD_ATTR_FLPT id="ddm_elements.v6_code_desc"></DD_ATTR_FLPT>
			<DD_ATTR_OEMD id="ddm_elements.v6_code_desc"></DD_ATTR_OEMD>
			<DD_ATTR_Y2KW id="ddm_elements.v6_code_desc"></DD_ATTR_Y2KW>
			<DD_ATTR_CASB id="ddm_elements.v6_code_desc"></DD_ATTR_CASB>
		</RECORD>
		<RECORD id="ddm_elements.v6_prox_or_days">
			<DD_DATA_NAME id="ddm_elements.v6_prox_or_days">V6_PROX_OR_DAYS </DD_DATA_NAME>
			<DD_DESCRIPTION id="ddm_elements.v6_prox_or_days">V6 Prox or Days</DD_DESCRIPTION>
			<DD_DATA_TYPE id="ddm_elements.v6_prox_or_days">C</DD_DATA_TYPE>
			<DD_DATA_LENGTH id="ddm_elements.v6_prox_or_days">1</DD_DATA_LENGTH>
			<DD_MASK_TYPE id="ddm_elements.v6_prox_or_days"></DD_MASK_TYPE>
			<DD_SYSTEM_REC id="ddm_elements.v6_prox_or_days"></DD_SYSTEM_REC>
			<ASC_COMP_ID id="ddm_elements.v6_prox_or_days">00000000</ASC_COMP_ID>
			<ASC_PROD_ID id="ddm_elements.v6_prox_or_days">V6H</ASC_PROD_ID>
			<LOCALIZATION_EX id="ddm_elements.v6_prox_or_days">N</LOCALIZATION_EX>
			<DD_CREATE_DATE id="ddm_elements.v6_prox_or_days">2457640</DD_CREATE_DATE>
			<DD_LSTREV_DATE id="ddm_elements.v6_prox_or_days">20160908</DD_LSTREV_DATE>
			<DD_AUTO_COMP id="ddm_elements.v6_prox_or_days"></DD_AUTO_COMP>
			<DD_ATTR_BLNK id="ddm_elements.v6_prox_or_days">N</DD_ATTR_BLNK>
			<DD_ATTR_CDAT id="ddm_elements.v6_prox_or_days"></DD_ATTR_CDAT>
			<DD_ATTR_CTLW id="ddm_elements.v6_prox_or_days"></DD_ATTR_CTLW>
			<DD_ATTR_CTLH id="ddm_elements.v6_prox_or_days"></DD_ATTR_CTLH>
			<DD_ATTR_CTYP id="ddm_elements.v6_prox_or_days">E</DD_ATTR_CTYP>
			<DD_ATTR_DCOL id="ddm_elements.v6_prox_or_days"></DD_ATTR_DCOL>
			<DD_ATTR_DCOM id="ddm_elements.v6_prox_or_days"></DD_ATTR_DCOM>
			<DD_ATTR_DEXP id="ddm_elements.v6_prox_or_days"></DD_ATTR_DEXP>
			<DD_ATTR_DFLT id="ddm_elements.v6_prox_or_days"></DD_ATTR_DFLT>
			<DD_ATTR_DKNM id="ddm_elements.v6_prox_or_days"></DD_ATTR_DKNM>
			<DD_ATTR_DKEY id="ddm_elements.v6_prox_or_days"></DD_ATTR_DKEY>
			<DD_ATTR_DTAB id="ddm_elements.v6_prox_or_days"></DD_ATTR_DTAB>
			<DD_ATTR_DINQ id="ddm_elements.v6_prox_or_days"></DD_ATTR_DINQ>
			<DD_ATTR_ENCR id="ddm_elements.v6_prox_or_days"></DD_ATTR_ENCR>
			<DD_ATTR_IDEF id="ddm_elements.v6_prox_or_days"></DD_ATTR_IDEF>
			<DD_ATTR_LABL id="ddm_elements.v6_prox_or_days">V6 Prox or Days</DD_ATTR_LABL>
			<DD_ATTR_LABS id="ddm_elements.v6_prox_or_days">V6 Prox or Days</DD_ATTR_LABS>
			<DD_ATTR_LDIS id="ddm_elements.v6_prox_or_days"></DD_ATTR_LDIS>
			<DD_ATTR_MAXL id="ddm_elements.v6_prox_or_days"></DD_ATTR_MAXL>
			<DD_ATTR_MAXR id="ddm_elements.v6_prox_or_days"></DD_ATTR_MAXR>
			<DD_ATTR_MAXV id="ddm_elements.v6_prox_or_days"></DD_ATTR_MAXV>
			<DD_ATTR_MINL id="ddm_elements.v6_prox_or_days"></DD_ATTR_MINL>
			<DD_ATTR_MINV id="ddm_elements.v6_prox_or_days"></DD_ATTR_MINV>
			<DD_ATTR_MSKI id="ddm_elements.v6_prox_or_days"></DD_ATTR_MSKI>
			<DD_ATTR_MSKO id="ddm_elements.v6_prox_or_days"></DD_ATTR_MSKO>
			<DD_ATTR_PADC id="ddm_elements.v6_prox_or_days"></DD_ATTR_PADC>
			<DD_ATTR_PADJ id="ddm_elements.v6_prox_or_days"></DD_ATTR_PADJ>
			<DD_ATTR_PREC id="ddm_elements.v6_prox_or_days">0</DD_ATTR_PREC>
			<DD_ATTR_PROM id="ddm_elements.v6_prox_or_days"></DD_ATTR_PROM>
			<DD_ATTR_PVAL id="ddm_elements.v6_prox_or_days"></DD_ATTR_PVAL>
			<DD_ATTR_SDLG id="ddm_elements.v6_prox_or_days"></DD_ATTR_SDLG>
			<DD_ATTR_SLEV id="ddm_elements.v6_prox_or_days"></DD_ATTR_SLEV>
			<DD_ATTR_STYP id="ddm_elements.v6_prox_or_days"></DD_ATTR_STYP>
			<DD_ATTR_STEP id="ddm_elements.v6_prox_or_days">0</DD_ATTR_STEP>
			<DD_ATTR_FLPT id="ddm_elements.v6_prox_or_days"></DD_ATTR_FLPT>
			<DD_ATTR_OEMD id="ddm_elements.v6_prox_or_days"></DD_ATTR_OEMD>
			<DD_ATTR_Y2KW id="ddm_elements.v6_prox_or_days"></DD_ATTR_Y2KW>
			<DD_ATTR_CASB id="ddm_elements.v6_prox_or_days"></DD_ATTR_CASB>
		</RECORD>
		<RECORD id="ddm_elements.v6_cred_hold">
			<DD_DATA_NAME id="ddm_elements.v6_cred_hold">V6_CRED_HOLD    </DD_DATA_NAME>
			<DD_DESCRIPTION id="ddm_elements.v6_cred_hold">V6 Cred Hold</DD_DESCRIPTION>
			<DD_DATA_TYPE id="ddm_elements.v6_cred_hold">C</DD_DATA_TYPE>
			<DD_DATA_LENGTH id="ddm_elements.v6_cred_hold">1</DD_DATA_LENGTH>
			<DD_MASK_TYPE id="ddm_elements.v6_cred_hold"></DD_MASK_TYPE>
			<DD_SYSTEM_REC id="ddm_elements.v6_cred_hold"></DD_SYSTEM_REC>
			<ASC_COMP_ID id="ddm_elements.v6_cred_hold">00000000</ASC_COMP_ID>
			<ASC_PROD_ID id="ddm_elements.v6_cred_hold">V6H</ASC_PROD_ID>
			<LOCALIZATION_EX id="ddm_elements.v6_cred_hold"></LOCALIZATION_EX>
			<DD_CREATE_DATE id="ddm_elements.v6_cred_hold">20160819</DD_CREATE_DATE>
			<DD_LSTREV_DATE id="ddm_elements.v6_cred_hold">20160819</DD_LSTREV_DATE>
			<DD_AUTO_COMP id="ddm_elements.v6_cred_hold"></DD_AUTO_COMP>
			<DD_ATTR_BLNK id="ddm_elements.v6_cred_hold"></DD_ATTR_BLNK>
			<DD_ATTR_CDAT id="ddm_elements.v6_cred_hold"></DD_ATTR_CDAT>
			<DD_ATTR_CTLW id="ddm_elements.v6_cred_hold"></DD_ATTR_CTLW>
			<DD_ATTR_CTLH id="ddm_elements.v6_cred_hold"></DD_ATTR_CTLH>
			<DD_ATTR_CTYP id="ddm_elements.v6_cred_hold">E</DD_ATTR_CTYP>
			<DD_ATTR_DCOL id="ddm_elements.v6_cred_hold"></DD_ATTR_DCOL>
			<DD_ATTR_DCOM id="ddm_elements.v6_cred_hold"></DD_ATTR_DCOM>
			<DD_ATTR_DEXP id="ddm_elements.v6_cred_hold"></DD_ATTR_DEXP>
			<DD_ATTR_DFLT id="ddm_elements.v6_cred_hold"></DD_ATTR_DFLT>
			<DD_ATTR_DKNM id="ddm_elements.v6_cred_hold"></DD_ATTR_DKNM>
			<DD_ATTR_DKEY id="ddm_elements.v6_cred_hold"></DD_ATTR_DKEY>
			<DD_ATTR_DTAB id="ddm_elements.v6_cred_hold"></DD_ATTR_DTAB>
			<DD_ATTR_DINQ id="ddm_elements.v6_cred_hold"></DD_ATTR_DINQ>
			<DD_ATTR_ENCR id="ddm_elements.v6_cred_hold"></DD_ATTR_ENCR>
			<DD_ATTR_IDEF id="ddm_elements.v6_cred_hold"></DD_ATTR_IDEF>
			<DD_ATTR_LABL id="ddm_elements.v6_cred_hold">V6 Cred Hold</DD_ATTR_LABL>
			<DD_ATTR_LABS id="ddm_elements.v6_cred_hold">V6 Cred Hold</DD_ATTR_LABS>
			<DD_ATTR_LDIS id="ddm_elements.v6_cred_hold"></DD_ATTR_LDIS>
			<DD_ATTR_MAXL id="ddm_elements.v6_cred_hold"></DD_ATTR_MAXL>
			<DD_ATTR_MAXR id="ddm_elements.v6_cred_hold"></DD_ATTR_MAXR>
			<DD_ATTR_MAXV id="ddm_elements.v6_cred_hold"></DD_ATTR_MAXV>
			<DD_ATTR_MINL id="ddm_elements.v6_cred_hold"></DD_ATTR_MINL>
			<DD_ATTR_MINV id="ddm_elements.v6_cred_hold"></DD_ATTR_MINV>
			<DD_ATTR_MSKI id="ddm_elements.v6_cred_hold"></DD_ATTR_MSKI>
			<DD_ATTR_MSKO id="ddm_elements.v6_cred_hold"></DD_ATTR_MSKO>
			<DD_ATTR_PADC id="ddm_elements.v6_cred_hold"></DD_ATTR_PADC>
			<DD_ATTR_PADJ id="ddm_elements.v6_cred_hold"></DD_ATTR_PADJ>
			<DD_ATTR_PREC id="ddm_elements.v6_cred_hold">0</DD_ATTR_PREC>
			<DD_ATTR_PROM id="ddm_elements.v6_cred_hold"></DD_ATTR_PROM>
			<DD_ATTR_PVAL id="ddm_elements.v6_cred_hold"></DD_ATTR_PVAL>
			<DD_ATTR_SDLG id="ddm_elements.v6_cred_hold"></DD_ATTR_SDLG>
			<DD_ATTR_SLEV id="ddm_elements.v6_cred_hold"></DD_ATTR_SLEV>
			<DD_ATTR_STYP id="ddm_elements.v6_cred_hold"></DD_ATTR_STYP>
			<DD_ATTR_STEP id="ddm_elements.v6_cred_hold"></DD_ATTR_STEP>
			<DD_ATTR_FLPT id="ddm_elements.v6_cred_hold"></DD_ATTR_FLPT>
			<DD_ATTR_OEMD id="ddm_elements.v6_cred_hold"></DD_ATTR_OEMD>
			<DD_ATTR_Y2KW id="ddm_elements.v6_cred_hold"></DD_ATTR_Y2KW>
			<DD_ATTR_CASB id="ddm_elements.v6_cred_hold"></DD_ATTR_CASB>
		</RECORD>
		<RECORD id="ddm_elements.v6_rsrvd_str">
			<DD_DATA_NAME id="ddm_elements.v6_rsrvd_str">V6_RSRVD_STR    </DD_DATA_NAME>
			<DD_DESCRIPTION id="ddm_elements.v6_rsrvd_str">V6 Rsrvd Str</DD_DESCRIPTION>
			<DD_DATA_TYPE id="ddm_elements.v6_rsrvd_str">C</DD_DATA_TYPE>
			<DD_DATA_LENGTH id="ddm_elements.v6_rsrvd_str">1</DD_DATA_LENGTH>
			<DD_MASK_TYPE id="ddm_elements.v6_rsrvd_str"></DD_MASK_TYPE>
			<DD_SYSTEM_REC id="ddm_elements.v6_rsrvd_str"></DD_SYSTEM_REC>
			<ASC_COMP_ID id="ddm_elements.v6_rsrvd_str">00000000</ASC_COMP_ID>
			<ASC_PROD_ID id="ddm_elements.v6_rsrvd_str">V6H</ASC_PROD_ID>
			<LOCALIZATION_EX id="ddm_elements.v6_rsrvd_str"></LOCALIZATION_EX>
			<DD_CREATE_DATE id="ddm_elements.v6_rsrvd_str">2457627</DD_CREATE_DATE>
			<DD_LSTREV_DATE id="ddm_elements.v6_rsrvd_str">20160826</DD_LSTREV_DATE>
			<DD_AUTO_COMP id="ddm_elements.v6_rsrvd_str"></DD_AUTO_COMP>
			<DD_ATTR_BLNK id="ddm_elements.v6_rsrvd_str"></DD_ATTR_BLNK>
			<DD_ATTR_CDAT id="ddm_elements.v6_rsrvd_str"></DD_ATTR_CDAT>
			<DD_ATTR_CTLW id="ddm_elements.v6_rsrvd_str"></DD_ATTR_CTLW>
			<DD_ATTR_CTLH id="ddm_elements.v6_rsrvd_str"></DD_ATTR_CTLH>
			<DD_ATTR_CTYP id="ddm_elements.v6_rsrvd_str">E</DD_ATTR_CTYP>
			<DD_ATTR_DCOL id="ddm_elements.v6_rsrvd_str"></DD_ATTR_DCOL>
			<DD_ATTR_DCOM id="ddm_elements.v6_rsrvd_str"></DD_ATTR_DCOM>
			<DD_ATTR_DEXP id="ddm_elements.v6_rsrvd_str"></DD_ATTR_DEXP>
			<DD_ATTR_DFLT id="ddm_elements.v6_rsrvd_str"></DD_ATTR_DFLT>
			<DD_ATTR_DKNM id="ddm_elements.v6_rsrvd_str"></DD_ATTR_DKNM>
			<DD_ATTR_DKEY id="ddm_elements.v6_rsrvd_str"></DD_ATTR_DKEY>
			<DD_ATTR_DTAB id="ddm_elements.v6_rsrvd_str"></DD_ATTR_DTAB>
			<DD_ATTR_DINQ id="ddm_elements.v6_rsrvd_str"></DD_ATTR_DINQ>
			<DD_ATTR_ENCR id="ddm_elements.v6_rsrvd_str"></DD_ATTR_ENCR>
			<DD_ATTR_IDEF id="ddm_elements.v6_rsrvd_str"></DD_ATTR_IDEF>
			<DD_ATTR_LABL id="ddm_elements.v6_rsrvd_str">V6 Rsrvd Str</DD_ATTR_LABL>
			<DD_ATTR_LABS id="ddm_elements.v6_rsrvd_str">V6 Rsrvd Str</DD_ATTR_LABS>
			<DD_ATTR_LDIS id="ddm_elements.v6_rsrvd_str"></DD_ATTR_LDIS>
			<DD_ATTR_MAXL id="ddm_elements.v6_rsrvd_str"></DD_ATTR_MAXL>
			<DD_ATTR_MAXR id="ddm_elements.v6_rsrvd_str"></DD_ATTR_MAXR>
			<DD_ATTR_MAXV id="ddm_elements.v6_rsrvd_str"></DD_ATTR_MAXV>
			<DD_ATTR_MINL id="ddm_elements.v6_rsrvd_str"></DD_ATTR_MINL>
			<DD_ATTR_MINV id="ddm_elements.v6_rsrvd_str"></DD_ATTR_MINV>
			<DD_ATTR_MSKI id="ddm_elements.v6_rsrvd_str"></DD_ATTR_MSKI>
			<DD_ATTR_MSKO id="ddm_elements.v6_rsrvd_str"></DD_ATTR_MSKO>
			<DD_ATTR_PADC id="ddm_elements.v6_rsrvd_str"></DD_ATTR_PADC>
			<DD_ATTR_PADJ id="ddm_elements.v6_rsrvd_str"></DD_ATTR_PADJ>
			<DD_ATTR_PREC id="ddm_elements.v6_rsrvd_str">0</DD_ATTR_PREC>
			<DD_ATTR_PROM id="ddm_elements.v6_rsrvd_str"></DD_ATTR_PROM>
			<DD_ATTR_PVAL id="ddm_elements.v6_rsrvd_str"></DD_ATTR_PVAL>
			<DD_ATTR_SDLG id="ddm_elements.v6_rsrvd_str"></DD_ATTR_SDLG>
			<DD_ATTR_SLEV id="ddm_elements.v6_rsrvd_str"></DD_ATTR_SLEV>
			<DD_ATTR_STYP id="ddm_elements.v6_rsrvd_str"></DD_ATTR_STYP>
			<DD_ATTR_STEP id="ddm_elements.v6_rsrvd_str">0</DD_ATTR_STEP>
			<DD_ATTR_FLPT id="ddm_elements.v6_rsrvd_str"></DD_ATTR_FLPT>
			<DD_ATTR_OEMD id="ddm_elements.v6_rsrvd_str"></DD_ATTR_OEMD>
			<DD_ATTR_Y2KW id="ddm_elements.v6_rsrvd_str"></DD_ATTR_Y2KW>
			<DD_ATTR_CASB id="ddm_elements.v6_rsrvd_str"></DD_ATTR_CASB>
		</RECORD>
		<RECORD id="ddm_elements.v6_disc_percent">
			<DD_DATA_NAME id="ddm_elements.v6_disc_percent">V6_DISC_PERCENT </DD_DATA_NAME>
			<DD_DESCRIPTION id="ddm_elements.v6_disc_percent">V6 Disc Percent</DD_DESCRIPTION>
			<DD_DATA_TYPE id="ddm_elements.v6_disc_percent">N</DD_DATA_TYPE>
			<DD_DATA_LENGTH id="ddm_elements.v6_disc_percent">7</DD_DATA_LENGTH>
			<DD_MASK_TYPE id="ddm_elements.v6_disc_percent"></DD_MASK_TYPE>
			<DD_SYSTEM_REC id="ddm_elements.v6_disc_percent"></DD_SYSTEM_REC>
			<ASC_COMP_ID id="ddm_elements.v6_disc_percent">00000000</ASC_COMP_ID>
			<ASC_PROD_ID id="ddm_elements.v6_disc_percent">V6H</ASC_PROD_ID>
			<LOCALIZATION_EX id="ddm_elements.v6_disc_percent">N</LOCALIZATION_EX>
			<DD_CREATE_DATE id="ddm_elements.v6_disc_percent">2457639</DD_CREATE_DATE>
			<DD_LSTREV_DATE id="ddm_elements.v6_disc_percent">20160907</DD_LSTREV_DATE>
			<DD_AUTO_COMP id="ddm_elements.v6_disc_percent"></DD_AUTO_COMP>
			<DD_ATTR_BLNK id="ddm_elements.v6_disc_percent">N</DD_ATTR_BLNK>
			<DD_ATTR_CDAT id="ddm_elements.v6_disc_percent"></DD_ATTR_CDAT>
			<DD_ATTR_CTLW id="ddm_elements.v6_disc_percent"></DD_ATTR_CTLW>
			<DD_ATTR_CTLH id="ddm_elements.v6_disc_percent"></DD_ATTR_CTLH>
			<DD_ATTR_CTYP id="ddm_elements.v6_disc_percent">N</DD_ATTR_CTYP>
			<DD_ATTR_DCOL id="ddm_elements.v6_disc_percent"></DD_ATTR_DCOL>
			<DD_ATTR_DCOM id="ddm_elements.v6_disc_percent"></DD_ATTR_DCOM>
			<DD_ATTR_DEXP id="ddm_elements.v6_disc_percent"></DD_ATTR_DEXP>
			<DD_ATTR_DFLT id="ddm_elements.v6_disc_percent"></DD_ATTR_DFLT>
			<DD_ATTR_DKNM id="ddm_elements.v6_disc_percent"></DD_ATTR_DKNM>
			<DD_ATTR_DKEY id="ddm_elements.v6_disc_percent"></DD_ATTR_DKEY>
			<DD_ATTR_DTAB id="ddm_elements.v6_disc_percent"></DD_ATTR_DTAB>
			<DD_ATTR_DINQ id="ddm_elements.v6_disc_percent"></DD_ATTR_DINQ>
			<DD_ATTR_ENCR id="ddm_elements.v6_disc_percent"></DD_ATTR_ENCR>
			<DD_ATTR_IDEF id="ddm_elements.v6_disc_percent"></DD_ATTR_IDEF>
			<DD_ATTR_LABL id="ddm_elements.v6_disc_percent">V6 Disc Percent</DD_ATTR_LABL>
			<DD_ATTR_LABS id="ddm_elements.v6_disc_percent">V6 Disc Percent</DD_ATTR_LABS>
			<DD_ATTR_LDIS id="ddm_elements.v6_disc_percent"></DD_ATTR_LDIS>
			<DD_ATTR_MAXL id="ddm_elements.v6_disc_percent"></DD_ATTR_MAXL>
			<DD_ATTR_MAXR id="ddm_elements.v6_disc_percent"></DD_ATTR_MAXR>
			<DD_ATTR_MAXV id="ddm_elements.v6_disc_percent"></DD_ATTR_MAXV>
			<DD_ATTR_MINL id="ddm_elements.v6_disc_percent"></DD_ATTR_MINL>
			<DD_ATTR_MINV id="ddm_elements.v6_disc_percent"></DD_ATTR_MINV>
			<DD_ATTR_MSKI id="ddm_elements.v6_disc_percent"></DD_ATTR_MSKI>
			<DD_ATTR_MSKO id="ddm_elements.v6_disc_percent"></DD_ATTR_MSKO>
			<DD_ATTR_PADC id="ddm_elements.v6_disc_percent"></DD_ATTR_PADC>
			<DD_ATTR_PADJ id="ddm_elements.v6_disc_percent"></DD_ATTR_PADJ>
			<DD_ATTR_PREC id="ddm_elements.v6_disc_percent">0</DD_ATTR_PREC>
			<DD_ATTR_PROM id="ddm_elements.v6_disc_percent"></DD_ATTR_PROM>
			<DD_ATTR_PVAL id="ddm_elements.v6_disc_percent"></DD_ATTR_PVAL>
			<DD_ATTR_SDLG id="ddm_elements.v6_disc_percent"></DD_ATTR_SDLG>
			<DD_ATTR_SLEV id="ddm_elements.v6_disc_percent"></DD_ATTR_SLEV>
			<DD_ATTR_STYP id="ddm_elements.v6_disc_percent"></DD_ATTR_STYP>
			<DD_ATTR_STEP id="ddm_elements.v6_disc_percent">0</DD_ATTR_STEP>
			<DD_ATTR_FLPT id="ddm_elements.v6_disc_percent"></DD_ATTR_FLPT>
			<DD_ATTR_OEMD id="ddm_elements.v6_disc_percent"></DD_ATTR_OEMD>
			<DD_ATTR_Y2KW id="ddm_elements.v6_disc_percent"></DD_ATTR_Y2KW>
			<DD_ATTR_CASB id="ddm_elements.v6_disc_percent"></DD_ATTR_CASB>
		</RECORD>
		<RECORD id="ddm_elements.v6_inv_days_due">
			<DD_DATA_NAME id="ddm_elements.v6_inv_days_due">V6_INV_DAYS_DUE </DD_DATA_NAME>
			<DD_DESCRIPTION id="ddm_elements.v6_inv_days_due">V6 Inv Days Due</DD_DESCRIPTION>
			<DD_DATA_TYPE id="ddm_elements.v6_inv_days_due">N</DD_DATA_TYPE>
			<DD_DATA_LENGTH id="ddm_elements.v6_inv_days_due">7</DD_DATA_LENGTH>
			<DD_MASK_TYPE id="ddm_elements.v6_inv_days_due"></DD_MASK_TYPE>
			<DD_SYSTEM_REC id="ddm_elements.v6_inv_days_due"></DD_SYSTEM_REC>
			<ASC_COMP_ID id="ddm_elements.v6_inv_days_due">00000000</ASC_COMP_ID>
			<ASC_PROD_ID id="ddm_elements.v6_inv_days_due">V6H</ASC_PROD_ID>
			<LOCALIZATION_EX id="ddm_elements.v6_inv_days_due">N</LOCALIZATION_EX>
			<DD_CREATE_DATE id="ddm_elements.v6_inv_days_due">2457640</DD_CREATE_DATE>
			<DD_LSTREV_DATE id="ddm_elements.v6_inv_days_due">20160908</DD_LSTREV_DATE>
			<DD_AUTO_COMP id="ddm_elements.v6_inv_days_due"></DD_AUTO_COMP>
			<DD_ATTR_BLNK id="ddm_elements.v6_inv_days_due">N</DD_ATTR_BLNK>
			<DD_ATTR_CDAT id="ddm_elements.v6_inv_days_due"></DD_ATTR_CDAT>
			<DD_ATTR_CTLW id="ddm_elements.v6_inv_days_due"></DD_ATTR_CTLW>
			<DD_ATTR_CTLH id="ddm_elements.v6_inv_days_due"></DD_ATTR_CTLH>
			<DD_ATTR_CTYP id="ddm_elements.v6_inv_days_due">N</DD_ATTR_CTYP>
			<DD_ATTR_DCOL id="ddm_elements.v6_inv_days_due"></DD_ATTR_DCOL>
			<DD_ATTR_DCOM id="ddm_elements.v6_inv_days_due"></DD_ATTR_DCOM>
			<DD_ATTR_DEXP id="ddm_elements.v6_inv_days_due"></DD_ATTR_DEXP>
			<DD_ATTR_DFLT id="ddm_elements.v6_inv_days_due"></DD_ATTR_DFLT>
			<DD_ATTR_DKNM id="ddm_elements.v6_inv_days_due"></DD_ATTR_DKNM>
			<DD_ATTR_DKEY id="ddm_elements.v6_inv_days_due"></DD_ATTR_DKEY>
			<DD_ATTR_DTAB id="ddm_elements.v6_inv_days_due"></DD_ATTR_DTAB>
			<DD_ATTR_DINQ id="ddm_elements.v6_inv_days_due"></DD_ATTR_DINQ>
			<DD_ATTR_ENCR id="ddm_elements.v6_inv_days_due"></DD_ATTR_ENCR>
			<DD_ATTR_IDEF id="ddm_elements.v6_inv_days_due"></DD_ATTR_IDEF>
			<DD_ATTR_LABL id="ddm_elements.v6_inv_days_due">V6 Inv Days Due</DD_ATTR_LABL>
			<DD_ATTR_LABS id="ddm_elements.v6_inv_days_due">V6 Inv Days Due</DD_ATTR_LABS>
			<DD_ATTR_LDIS id="ddm_elements.v6_inv_days_due"></DD_ATTR_LDIS>
			<DD_ATTR_MAXL id="ddm_elements.v6_inv_days_due"></DD_ATTR_MAXL>
			<DD_ATTR_MAXR id="ddm_elements.v6_inv_days_due"></DD_ATTR_MAXR>
			<DD_ATTR_MAXV id="ddm_elements.v6_inv_days_due"></DD_ATTR_MAXV>
			<DD_ATTR_MINL id="ddm_elements.v6_inv_days_due"></DD_ATTR_MINL>
			<DD_ATTR_MINV id="ddm_elements.v6_inv_days_due"></DD_ATTR_MINV>
			<DD_ATTR_MSKI id="ddm_elements.v6_inv_days_due"></DD_ATTR_MSKI>
			<DD_ATTR_MSKO id="ddm_elements.v6_inv_days_due"></DD_ATTR_MSKO>
			<DD_ATTR_PADC id="ddm_elements.v6_inv_days_due"></DD_ATTR_PADC>
			<DD_ATTR_PADJ id="ddm_elements.v6_inv_days_due"></DD_ATTR_PADJ>
			<DD_ATTR_PREC id="ddm_elements.v6_inv_days_due">0</DD_ATTR_PREC>
			<DD_ATTR_PROM id="ddm_elements.v6_inv_days_due"></DD_ATTR_PROM>
			<DD_ATTR_PVAL id="ddm_elements.v6_inv_days_due"></DD_ATTR_PVAL>
			<DD_ATTR_SDLG id="ddm_elements.v6_inv_days_due"></DD_ATTR_SDLG>
			<DD_ATTR_SLEV id="ddm_elements.v6_inv_days_due"></DD_ATTR_SLEV>
			<DD_ATTR_STYP id="ddm_elements.v6_inv_days_due"></DD_ATTR_STYP>
			<DD_ATTR_STEP id="ddm_elements.v6_inv_days_due">0</DD_ATTR_STEP>
			<DD_ATTR_FLPT id="ddm_elements.v6_inv_days_due"></DD_ATTR_FLPT>
			<DD_ATTR_OEMD id="ddm_elements.v6_inv_days_due"></DD_ATTR_OEMD>
			<DD_ATTR_Y2KW id="ddm_elements.v6_inv_days_due"></DD_ATTR_Y2KW>
			<DD_ATTR_CASB id="ddm_elements.v6_inv_days_due"></DD_ATTR_CASB>
		</RECORD>
		<RECORD id="ddm_elements.v6_disc_days">
			<DD_DATA_NAME id="ddm_elements.v6_disc_days">V6_DISC_DAYS    </DD_DATA_NAME>
			<DD_DESCRIPTION id="ddm_elements.v6_disc_days">V6 Disc Days</DD_DESCRIPTION>
			<DD_DATA_TYPE id="ddm_elements.v6_disc_days">N</DD_DATA_TYPE>
			<DD_DATA_LENGTH id="ddm_elements.v6_disc_days">7</DD_DATA_LENGTH>
			<DD_MASK_TYPE id="ddm_elements.v6_disc_days"></DD_MASK_TYPE>
			<DD_SYSTEM_REC id="ddm_elements.v6_disc_days"></DD_SYSTEM_REC>
			<ASC_COMP_ID id="ddm_elements.v6_disc_days">00000000</ASC_COMP_ID>
			<ASC_PROD_ID id="ddm_elements.v6_disc_days">V6H</ASC_PROD_ID>
			<LOCALIZATION_EX id="ddm_elements.v6_disc_days">N</LOCALIZATION_EX>
			<DD_CREATE_DATE id="ddm_elements.v6_disc_days">2457640</DD_CREATE_DATE>
			<DD_LSTREV_DATE id="ddm_elements.v6_disc_days">20160908</DD_LSTREV_DATE>
			<DD_AUTO_COMP id="ddm_elements.v6_disc_days"></DD_AUTO_COMP>
			<DD_ATTR_BLNK id="ddm_elements.v6_disc_days">N</DD_ATTR_BLNK>
			<DD_ATTR_CDAT id="ddm_elements.v6_disc_days"></DD_ATTR_CDAT>
			<DD_ATTR_CTLW id="ddm_elements.v6_disc_days"></DD_ATTR_CTLW>
			<DD_ATTR_CTLH id="ddm_elements.v6_disc_days"></DD_ATTR_CTLH>
			<DD_ATTR_CTYP id="ddm_elements.v6_disc_days">N</DD_ATTR_CTYP>
			<DD_ATTR_DCOL id="ddm_elements.v6_disc_days"></DD_ATTR_DCOL>
			<DD_ATTR_DCOM id="ddm_elements.v6_disc_days"></DD_ATTR_DCOM>
			<DD_ATTR_DEXP id="ddm_elements.v6_disc_days"></DD_ATTR_DEXP>
			<DD_ATTR_DFLT id="ddm_elements.v6_disc_days"></DD_ATTR_DFLT>
			<DD_ATTR_DKNM id="ddm_elements.v6_disc_days"></DD_ATTR_DKNM>
			<DD_ATTR_DKEY id="ddm_elements.v6_disc_days"></DD_ATTR_DKEY>
			<DD_ATTR_DTAB id="ddm_elements.v6_disc_days"></DD_ATTR_DTAB>
			<DD_ATTR_DINQ id="ddm_elements.v6_disc_days"></DD_ATTR_DINQ>
			<DD_ATTR_ENCR id="ddm_elements.v6_disc_days"></DD_ATTR_ENCR>
			<DD_ATTR_IDEF id="ddm_elements.v6_disc_days"></DD_ATTR_IDEF>
			<DD_ATTR_LABL id="ddm_elements.v6_disc_days">V6 Disc Days</DD_ATTR_LABL>
			<DD_ATTR_LABS id="ddm_elements.v6_disc_days">V6 Disc Days</DD_ATTR_LABS>
			<DD_ATTR_LDIS id="ddm_elements.v6_disc_days"></DD_ATTR_LDIS>
			<DD_ATTR_MAXL id="ddm_elements.v6_disc_days"></DD_ATTR_MAXL>
			<DD_ATTR_MAXR id="ddm_elements.v6_disc_days"></DD_ATTR_MAXR>
			<DD_ATTR_MAXV id="ddm_elements.v6_disc_days"></DD_ATTR_MAXV>
			<DD_ATTR_MINL id="ddm_elements.v6_disc_days"></DD_ATTR_MINL>
			<DD_ATTR_MINV id="ddm_elements.v6_disc_days"></DD_ATTR_MINV>
			<DD_ATTR_MSKI id="ddm_elements.v6_disc_days"></DD_ATTR_MSKI>
			<DD_ATTR_MSKO id="ddm_elements.v6_disc_days"></DD_ATTR_MSKO>
			<DD_ATTR_PADC id="ddm_elements.v6_disc_days"></DD_ATTR_PADC>
			<DD_ATTR_PADJ id="ddm_elements.v6_disc_days"></DD_ATTR_PADJ>
			<DD_ATTR_PREC id="ddm_elements.v6_disc_days">0</DD_ATTR_PREC>
			<DD_ATTR_PROM id="ddm_elements.v6_disc_days"></DD_ATTR_PROM>
			<DD_ATTR_PVAL id="ddm_elements.v6_disc_days"></DD_ATTR_PVAL>
			<DD_ATTR_SDLG id="ddm_elements.v6_disc_days"></DD_ATTR_SDLG>
			<DD_ATTR_SLEV id="ddm_elements.v6_disc_days"></DD_ATTR_SLEV>
			<DD_ATTR_STYP id="ddm_elements.v6_disc_days"></DD_ATTR_STYP>
			<DD_ATTR_STEP id="ddm_elements.v6_disc_days">0</DD_ATTR_STEP>
			<DD_ATTR_FLPT id="ddm_elements.v6_disc_days"></DD_ATTR_FLPT>
			<DD_ATTR_OEMD id="ddm_elements.v6_disc_days"></DD_ATTR_OEMD>
			<DD_ATTR_Y2KW id="ddm_elements.v6_disc_days"></DD_ATTR_Y2KW>
			<DD_ATTR_CASB id="ddm_elements.v6_disc_days"></DD_ATTR_CASB>
		</RECORD>
	</ALIAS>
</ARM10A>
